Workbook

Sheet Sheet2
C1: Q1- which broader category having higher contribution in CPI
C10: Year-month | D10: (All)
A12: for all years | C12: Average of Education | D12: Average of Food and beverages | E12: Average of Household goods and services | F12: Average of Transport and communication | G12: Average of Fuel and light | H12: Average of Recreation and amusement | I12: Average of Personal care and effects | J12: Average of Pan, tobacco and intoxicants | K12: Average of Health | L12: Average of Housing | M12: Average of Miscellaneous | N12: Average of Clothing and footwear
C13: 141.13115 | D13: 142.51003 | E13: 136.68689 | F13: 127.17049 | G13: 136.51003 | H13: 133.8918 | I13: 133.35 | J13: 155.38579 | K13: 138.5168 | L13: 139.256 | M13: 134.23579 | N13: 141.67432
C15: Average of Education | D15: Average of Food and beverages | E15: Average of Household goods and services | F15: Average of Transport and communication | G15: Average of Fuel and light | H15: Average of Recreation and amusement | I15: Average of Personal care and effects | J15: Average of Pan, tobacco and intoxicants | K15: Average of Health | L15: Average of Housing | M15: Average of Miscellaneous | N15: Average of Clothing and footwear
C16: 141.13115 | D16: 142.51003 | E16: 136.68689 | F16: 127.17049 | G16: 136.51003 | H16: 133.8918 | I16: 133.35 | J16: 155.38579 | K16: 138.5168 | L16: 139.256 | M16: 134.23579 | N16: 141.67432
C17: =C16/1660.32*100 -> 8.5002378 | D17: =D16/1660.32*100 -> 8.5832868 | E17: =E16/1660.32*100 -> 8.2325627 | F17: =F16/1660.32*100 -> 7.6593965 | G17: =G16/1660.32*100 -> 8.2219107 | H17: =H16/1660.32*100 -> 8.0642167 | I17: =I16/1660.32*100 -> 8.0315843 | J17: =J16/1660.32*100 -> 9.3587858 | ... N17: =N16/1660.32*100 -> 8.5329525
C18: Average of Education | D18: Average of Food and beverages | E18: Average of Household goods and services | F18: Average of Transport and communication | G18: Average of Fuel and light | H18: Average of Recreation and amusement | I18: Average of Personal care and effects | J18: Average of Pan, tobacco and intoxicants | K18: Average of Health | L18: Average of Housing | M18: Average of Miscellaneous | N18: Average of Clothing and footwear
C19: =C16/1660.32*100 -> 8.5002378 | D19: =D16/1660.32*100 -> 8.5832868 | E19: =E16/1660.32*100 -> 8.2325627 | F19: =F16/1660.32*100 -> 7.6593965 | G19: =G16/1660.32*100 -> 8.2219107 | H19: =H16/1660.32*100 -> 8.0642167 | I19: =I16/1660.32*100 -> 8.0315843 | J19: =J16/1660.32*100 -> 9.3587858 | ... N19: =N16/1660.32*100 -> 8.5329525
A22: for Latest Month may 2023 | C22: Average of Education | D22: Average of Food and beverages | E22: Average of Household goods and services | F22: Average of Transport and communication | G22: Average of Fuel and light | H22: Average of Recreation and amusement | I22: Average of Personal care and effects | J22: Average of Pan, tobacco and intoxicants | K22: Average of Health | L22: Average of Housing | M22: Average of Miscellaneous | N22: Average of Clothing and footwear
C23: 177.4 | D23: 179.66667 | E23: 175.03333 | F23: 164.96667 | G23: 182.9 | H23: 171.4 | I23: 185.23333 | J23: 201.7 | K23: 185.23333 | L23: 163.48333 | M23: 175.6 | N23: 185.43333
C24: =C23/2148.05*100 -> 8.2586532 | D24: =D23/2148.05*100 -> 8.3641753 | E24: =E23/2148.05*100 -> 8.1484757 | F24: =F23/2148.05*100 -> 7.6798336 | G24: =G23/2148.05*100 -> 8.5146994 | H24: =H23/2148.05*100 -> 7.9793301 | I24: =I23/2148.05*100 -> 8.623325 | J24: =J23/2148.05*100 -> 9.3899118 | ... N24: =N23/2148.05*100 -> 8.6326358
C27: As we can see Pan,tabacco and intoxicants category having the higher contribution towards CPI 9.36% in yearly pattern and for latest month may 2023 it is 9.39%
A63: Q2 - Which Year having YOY growth more after 2017 and also reasons
C68: Row Labels | D68: Average of General index
C69: 2013 | D69: 110.01389
C70: 2014 | D70: 117.32778
C71: 2015 | D71: 123.03611
C72: 2016 | D72: 129.1
C73: 2017 | D73: 133.38611
C74: 2018 | D74: 138.66944
C75: 2019 | D75: 144.12727
C76: 2020 | D76: 153.33
C77: 2021 | D77: 161.41667
C78: 2022 | D78: 172.075
C79: 2023 | D79: 177.57333
C80: Grand Total | D80: 139.56448
D83: Years | E83: Y-O-Y Growth | F83: Avg
D84: 2017 | F84: 133.38611
D85: 2018 | E85: =(F85-F84)/F84*100 -> 3.9609321 | F85: 138.66944
D86: 2019 | E86: =(F86-F85)/F85*100 -> 3.935855 | F86: 144.12727
D87: 2020 | E87: =(F87-F86)/F86*100 -> 6.3851394 | F87: 153.33
D88: 2021 | E88: =(F88-F87)/F87*100 -> 5.2740277 | F88: 161.41667
D89: 2022 | E89: =(F89-F88)/F88*100 -> 6.6029943 | F89: 172.075
D90: 2023 | E90: =(F90-F89)/F89*100 -> 3.1953121 | F90: 177.57333
A92: As we can see in year 2022 the yoy growth is 6.60% which is maximum among all other years
F94: possible reasons
F95: 1-Russia–Ukraine War
F96: 2-High Fuel Prices
F97: 3-Global Supply Chain Disruptions
F98: 4-Post-COVID Economic Recovery
B102: Q3- Month with highest and lowest food Inflation
C114: Row Labels | D114: Average of Food and beverages
C115: 2022 | D115: 177.3619
C116: Jun | D116: 175.53333
C117: Jul | D117: 175.63333
C118: Aug | D118: 176.86667
C119: Sep | D119: 178.36667
C120: Oct | D120: 180.1
C121: Nov | D121: 178.73333
C122: Dec | D122: 176.3
C123: 2023 | D123: 178.05333
C124: Jan | D124: 177.06667
C125: Feb | D125: 177.5
C126: Mar | D126: 177.53333
... C129: Grand Total | D129: 177.65
D131: months(2022-2023) | E131: Avg of food and bvg | F131: MOM Change %
D132: Jun | E132: 175.53333
D133: Jul | E133: 175.63333 | F133: =(E133-E132)/E132*100 -> 0.056969237
D134: Aug | E134: 176.86667 | F134: =(E134-E133)/E133*100 -> 0.70222054 | H134: October | I134: =MAX(F133:F143) -> 0.97178098
D135: Sep | E135: 178.36667 | F135: =(E135-E134)/E134*100 -> 0.84809649 | H135: December | I135: =MIN(F133:F143) -> -1.3614323
D136: Oct | E136: 180.1 | F136: =(E136-E135)/E135*100 -> 0.97178098
D137: Nov | E137: 178.73333 | F137: =(E137-E136)/E136*100 -> -0.75883768 | H137: Highest food inflation in month October 2022 and lowest is December 2022
D138: Dec | E138: 176.3 | F138: =(E138-E137)/E137*100 -> -1.3614323
D139: Jan | E139: 177.06667 | F139: =(E139-E138)/E138*100 -> 0.43486481
D140: Feb | E140: 177.5 | F140: =(E140-E139)/E139*100 -> 0.24472892
D141: Mar | E141: 177.53333 | F141: =(E141-E140)/E140*100 -> 0.018779343
D142: Apr | E142: 178.5 | F142: =(E142-E141)/E141*100 -> 0.54449869
D143: May | E143: 179.66667 | F143: =(E143-E142)/E142*100 -> 0.65359477
A147: 3-b Identify the Absolute change and also from food bucket which individual contribute most towards inflation
C158: Row Labels | D158: Average of Cereals and products | E158: Average of Non-alcoholic beverages | F158: Average of Sugar and Confectionery | G158: Average of Food and beverages | H158: Average of Prepared meals, snacks, sweets etc. | I158: Average of Milk and products | J158: Average of Vegetables | K158: Average of Spices | L158: Average of Pulses and products | M158: Average of Meat and fish | N158: Average of Oils and fats | O158: Average of Fruits | P158: Average of Egg
C159: 2022
C160: Jun | D160: 155.43333 | E160: 167.06667 | F160: 120.13333 | G160: 175.53333 | H160: 184.03333 | I160: 165.86667 | J160: 187.03333 | K160: 186.5 | L160: 164.16667 | M160: 220 | N160: 199.2 | O160: 169.86667 | P160: 171.06667
C161: Jul | D161: 157 | E161: 167.56667 | F161: 120.23333 | G161: 175.63333 | H161: 185.33333 | I161: 166.66667 | J161: 186.4 | K161: 189.36667 | L161: 164.23333 | M161: 213.63333 | N161: 194.26667 | O161: 174.43333 | P161: 175.36667
C162: Aug | D162: 160.63333 | E162: 168.03333 | F162: 121.1 | G162: 176.86667 | H162: 186.4 | I162: 168.13333 | J162: 190.96667 | K162: 192.96667 | L162: 167.2 | M162: 207.16667 | N162: 191 | O162: 173.06667 | P162: 169.36667
C163: Sep | D163: 163.76667 | E163: 168.63333 | F163: 121.83333 | G163: 178.36667 | H163: 187.53333 | I163: 169.76667 | J163: 196.5 | K163: 196.66667 | L163: 169.1 | M163: 209.86667 | N163: 187.36667 | O163: 165.76667 | P163: 169.86667
C164: Oct | D164: 165.43333 | E164: 169.1 | F164: 122.13333 | G164: 180.1 | H164: 188.46667 | I164: 170.93333 | J164: 204.36667 | K164: 199.3 | L164: 169.8 | M164: 211.53333 | N164: 185.26667 | O164: 163.9 | P164: 171.03333
C165: Nov | D165: 167.56667 | E165: 169.63333 | F165: 122.33333 | G165: 178.73333 | H165: 189.6 | I165: 172.3 | J165: 186.73333 | K165: 202.13333 | L165: 170.56667 | M165: 210 | N165: 187.63333 | O165: 160.8 | P165: 181.6
C166: Dec | D166: 169.4 | E166: 170.2 | F166: 122.03333 | G166: 176.3 | H166: 190.43333 | I166: 173.63333 | J166: 162.93333 | K166: 204.4 | L166: 170.86667 | M166: 209.6 | N166: 187.16667 | O166: 158.06667 | P166: 190.4
C167: 2023
C168: Jan | D168: 173.7 | E168: 170.66667 | F168: 121.36667 | G168: 177.06667 | H168: 191.33333 | I168: 174.7 | J168: 157.36667 | K168: 207.73333 | L168: 170.93333 | M168: 211.4 | N168: 185.93333 | O168: 158.36667 | P168: 194.8
C169: Feb | D169: 174.43333 | E169: 171.6 | F169: 120.33333 | G169: 177.5 | H169: 193.16667 | I169: 177.4 | J169: 156.46667 | K169: 208.86667 | L169: 171.2 | M169: 208.36667 | N169: 178.3 | O169: 169.6 | P169: 175.43333
C170: Mar | D170: 174.46667 | E170: 171.6 | F170: 120.33333 | G170: 177.53333 | H170: 193.16667 | I170: 177.4 | J170: 156.53333 | K170: 208.86667 | L170: 171.26667 | M170: 208.36667 | N170: 178.23333 | O170: 169.6 | P170: 175.43333
C171: Apr | D171: 173.96667 | E171: 172.2 | F171: 121.6 | G171: 178.5 | H171: 193.66667 | I171: 178.46667 | J171: 159.36667 | K171: 212.06667 | L171: 173.63333 | M171: 209.96667 | N171: 174.03333 | O171: 176.4 | P171: 169.96667
C172: May | D172: 173.86667 | E172: 172.66667 | F172: 122.93333 | G172: 179.66667 | H172: 194.33333 | I172: 179.5 | J172: 164.9 | K172: 216.96667 | L172: 175.8 | M172: 215.06667 | N172: 169.23333 | O172: 172.33333 | P172: 173.63333
C173: Grand Total | D173: 167.47222 | E173: 169.91389 | F173: 121.36389 | G173: 177.65 | H173: 189.78889 | I173: 172.89722 | J173: 175.79722 | K173: 202.15278 | L173: 169.89722 | M173: 211.24722 | N173: 184.80278 | O173: 167.68333 | P173: 176.49722
D177: Average of Cereals and products | E177: Average of Non-alcoholic beverages | F177: Average of Sugar and Confectionery | G177: Average of Food and beverages | H177: Average of Prepared meals, snacks, sweets etc. | I177: Average of Milk and products | J177: Average of Vegetables | K177: Average of Spices | L177: Average of Pulses and products | M177: Average of Meat and fish | N177: Average of Oils and fats | O177: Average of Fruits | P177: Average of Egg
C178: Average | D178: 167.47222 | E178: 169.91389 | F178: 121.36389 | G178: 177.65 | H178: 189.78889 | I178: 172.89722 | J178: 175.79722 | K178: 202.15278 | L178: 169.89722 | M178: 211.24722 | N178: 184.80278 | O178: 167.68333 | P178: 176.49722
C179: 45047 | D179: 173.86667 | E179: 172.66667 | F179: 122.93333 | G179: 179.66667 | H179: 194.33333 | I179: 179.5 | J179: 164.9 | K179: 216.96667 | L179: 175.8 | M179: 215.06667 | N179: 169.23333 | O179: 172.33333 | P179: 173.63333
C180: 44713 | D180: 155.43333 | E180: 167.06667 | F180: 120.13333 | G180: 175.53333 | H180: 184.03333 | I180: 165.86667 | J180: 187.03333 | K180: 186.5 | L180: 164.16667 | M180: 220 | N180: 199.2 | O180: 169.86667 | P180: 171.06667
C181: absolute change | D181: =D179-D180 -> 18.433333 | E181: =E179-E180 -> 5.6 | F181: =F179-F180 -> 2.8 | G181: =G179-G180 -> 4.1333333 | H181: =H179-H180 -> 10.3 | I181: =I179-I180 -> 13.633333 | J181: =J179-J180 -> -22.133333 | K181: =K179-K180 -> 30.466667 | ... P181: =P179-P180 -> 2.5666667
E183: Food and beverages have 4.133 of absolute change while spices contribute most absolute change with 30.46
A192: Q4 - How covid-19 affect the inflation investigate
C201: Row Labels | D201: Average of Food and beverages | E201: Average of Fuel and light | F201: Average of Household goods and services | G201: Average of Health | H201: Average of General index
C202: 2017 | D202: 136.84722 | E202: 129.28056 | F202: 131.69444 | G202: 128.93889 | H202: 133.38611
C203: 2018 | D203: 138.99167 | E203: 138.29722 | F203: 138.35833 | G203: 137.00556 | H203: 138.66944
C204: 2019 | D204: 144.88485 | E204: 138.77576 | F204: 144.13636 | G204: 146.92424 | H204: 144.12727
C205: 2020 | D205: 151.12222 | E205: 145.8 | F205: 146.14444 | G205: 150.77778 | H205: 149.24444
C206: Grand Total | D206: 140.97807 | E206: 136.1807 | F206: 138.54123 | G206: 138.41667 | H206: 139.41579
C210: Row Labels | D210: Average of Food and beverages | E210: Average of Fuel and light | F210: Average of Household goods and services | G210: Average of Health | H210: Average of General index
...

Sheet All_India_Index_Upto_April23 (1
A1: Sector | B1: Year | C1: Month | D1: Year-month | E1: Cereals and products | F1: Meat and fish | G1: Egg | H1: Milk and products | I1: Oils and fats | J1: Fruits | K1: Vegetables | L1: Pulses and products | M1: Sugar and Confectionery | N1: Spices | O1: Non-alcoholic beverages | P1: Prepared meals, snacks, sweets etc. | Q1: Food and beverages | R1: MOM for Food nad beverages | S1: Pan, tobacco and intoxicants | T1: MOM for Pan,etc | U1: Clothing | V1: Footwear | W1: Clothing and footwear | X1: MOM for Clothing and Footwear | Y1: Housing | Z1: Fuel and light | AA1: MOM for Fuel and Light | AB1: Household goods and services | AC1: MOM for Household Goods and etc | AD1: Health | AE1: MOM for Health | AF1: Transport and communication | AG1: MOM for Transport and etc | AH1: Recreation and amusement | AI1: MOM for recreation and amusement | AJ1: Education | AK1: MOM for eduction | AL1: Personal care and effects | AM1: MOM for Personal care and effect | AN1: Miscellaneous | AO1: MOM for Miscellinous | AP1: General index | AQ1: MOM for Genral index
A2: Rural | B2: 2013 | C2: January | D2: =DATE(B2,MATCH(TRIM(C2),{"January","February","March","April","May","June","July","August","September","October","November","December"},0),1) -> 41275 | E2: 107.5 | F2: 106.3 | G2: 108.1 | H2: 104.9 | I2: 106.1 | J2: 103.9 | K2: 101.9 | L2: 106.1 | M2: 106.8 | N2: 103.1 | O2: 104.8 | P2: 106.7 | Q2: 105.5 | S2: 105.1 | U2: 106.5 | V2: 105.8 | W2: 106.4 | Y2: NA | Z2: 105.5 | AB2: 104.8 | AD2: 104 | AF2: 103.3 | AH2: 103.4 | AJ2: 103.8 | AL2: 104.7 | AN2: 104 | AP2: 105.1
A3: Urban | B3: 2013 | C3: January | D3: =DATE(B3,MATCH(TRIM(C3),{"January","February","March","April","May","June","July","August","September","October","November","December"},0),1) -> 41275 | E3: 110.5 | F3: 109.1 | G3: 113 | H3: 103.6 | I3: 103.4 | J3: 102.3 | K3: 102.9 | L3: 105.8 | M3: 105.1 | N3: 101.8 | O3: 105.1 | P3: 107.9 | Q3: 105.9 | S3: 105.2 | U3: 105.9 | V3: 105 | W3: 105.8 | Y3: 100.3 | Z3: 105.4 | AB3: 104.8 | AD3: 104.1 | AF3: 103.2 | AH3: 102.9 | AJ3: 103.5 | AL3: 104.3 | AN3: 103.7 | AP3: 104
A4: Rural+Urban | B4: 2013 | C4: January | D4: =DATE(B4,MATCH(TRIM(C4),{"January","February","March","April","May","June","July","August","September","October","November","December"},0),1) -> 41275 | E4: 108.4 | F4: 107.3 | G4: 110 | H4: 104.4 | I4: 105.1 | J4: 103.2 | K4: 102.2 | L4: 106 | M4: 106.2 | N4: 102.7 | O4: 104.9 | P4: 107.3 | Q4: 105.6 | S4: 105.1 | U4: 106.3 | V4: 105.5 | W4: 106.2 | Y4: 100.3 | Z4: 105.5 | AB4: 104.8 | AD4: 104 | AF4: 103.2 | AH4: 103.1 | AJ4: 103.6 | AL4: 104.5 | AN4: 103.9 | AP4: 104.6
A5: Rural | B5: 2013 | C5: February | D5: =DATE(B5,MATCH(TRIM(C5),{"January","February","March","April","May","June","July","August","September","October","November","December"},0),1) -> 41306 | E5: 109.2 | F5: 108.7 | G5: 110.2 | H5: 105.4 | I5: 106.7 | J5: 104 | K5: 102.4 | L5: 105.9 | M5: 105.7 | N5: 103.1 | O5: 105.1 | P5: 107.7 | Q5: 106.3 | S5: 105.6 | U5: 107.1 | V5: 106.3 | W5: 107 | Y5: NA | Z5: 106.2 | AB5: 105.2 | AD5: 104.4 | AF5: 103.9 | AH5: 104 | AJ5: 104.1 | AL5: 104.6 | AN5: 104.4 | AP5: 105.8
A6: Urban | B6: 2013 | C6: February | D6: =DATE(B6,MATCH(TRIM(C6),{"January","February","March","April","May","June","July","August","September","October","November","December"},0),1) -> 41306 | E6: 112.9 | F6: 112.9 | G6: 116.9 | H6: 104 | I6: 103.5 | J6: 103.1 | K6: 104.9 | L6: 104.1 | M6: 103.8 | N6: 102.3 | O6: 106 | P6: 109 | Q6: 107.2 | S6: 106 | U6: 106.6 | V6: 105.5 | W6: 106.4 | Y6: 100.4 | Z6: 105.7 | AB6: 105.2 | AD6: 104.7 | AF6: 104.4 | AH6: 103.3 | AJ6: 103.7 | AL6: 104.3 | AN6: 104.3 | AP6: 104.7
A7: Rural+Urban | B7: 2013 | C7: February | D7: =DATE(B7,MATCH(TRIM(C7),{"January","February","March","April","May","June","July","August","September","October","November","December"},0),1) -> 41306 | E7: 110.4 | F7: 110.2 | G7: 112.8 | H7: 104.9 | I7: 105.5 | J7: 103.6 | K7: 103.2 | L7: 105.3 | M7: 105.1 | N7: 102.8 | O7: 105.5 | P7: 108.3 | Q7: 106.6 | S7: 105.7 | U7: 106.9 | V7: 106 | W7: 106.8 | Y7: 100.4 | Z7: 106 | AB7: 105.2 | AD7: 104.5 | AF7: 104.2 | AH7: 103.6 | AJ7: 103.9 | AL7: 104.5 | AN7: 104.4 | AP7: 105.3
A8: Rural | B8: 2013 | C8: March | D8: =DATE(B8,MATCH(TRIM(C8),{"January","February","March","April","May","June","July","August","September","October","November","December"},0),1) -> 41334 | E8: 110.2 | F8: 108.8 | G8: 109.9 | H8: 105.6 | I8: 106.2 | J8: 105.7 | K8: 101.4 | L8: 105.7 | M8: 105 | N8: 103.3 | O8: 105.6 | P8: 108.2 | Q8: 106.6 | S8: 106.5 | U8: 107.6 | V8: 106.8 | W8: 107.5 | Y8: NA | Z8: 106.1 | AB8: 105.6 | AD8: 104.7 | AF8: 104.6 | AH8: 104 | AJ8: 104.3 | AL8: 104.3 | AN8: 104.6 | AP8: 106
A9: Urban | B9: 2013 | C9: March | D9: =DATE(B9,MATCH(TRIM(C9),{"January","February","March","April","May","June","July","August","September","October","November","December"},0),1) -> 41334 | E9: 113.9 | F9: 111.4 | G9: 113.2 | H9: 104.3 | I9: 102.7 | J9: 104.9 | K9: 103.8 | L9: 103.5 | M9: 102.6 | N9: 102.4 | O9: 107 | P9: 109.8 | Q9: 107.3 | S9: 106.8 | U9: 107.2 | V9: 106 | W9: 107 | Y9: 100.4 | Z9: 106 | AB9: 105.7 | AD9: 105.2 | AF9: 105.5 | AH9: 103.5 | AJ9: 103.8 | AL9: 104.2 | AN9: 104.9 | AP9: 105
A10: Rural+Urban | B10: 2013 | C10: March | D10: =DATE(B10,MATCH(TRIM(C10),{"January","February","March","April","May","June","July","August","September","October","November","December"},0),1) -> 41334 | E10: 111.4 | F10: 109.7 | G10: 111.2 | H10: 105.1 | I10: 104.9 | J10: 105.3 | K10: 102.2 | L10: 105 | M10: 104.2 | N10: 103 | O10: 106.2 | P10: 108.9 | Q10: 106.9 | S10: 106.6 | U10: 107.4 | V10: 106.5 | W10: 107.3 | Y10: 100.4 | Z10: 106.1 | AB10: 105.6 | AD10: 104.9 | AF10: 105.1 | AH10: 103.7 | AJ10: 104 | AL10: 104.3 | AN10: 104.7 | AP10: 105.5
A11: Rural | B11: 2013 | C11: April | D11: =DATE(B11,MATCH(TRIM(C11),{"January","February","March","April","May","June","July","August","September","October","November","December"},0),1) -> 41365 | E11: 110.2 | F11: 109.5 | G11: 106.9 | H11: 106.3 | I11: 105.7 | J11: 108.3 | K11: 103.4 | L11: 105.7 | M11: 104.2 | N11: 103.2 | O11: 106.5 | P11: 108.8 | Q11: 107.1 | S11: 107.1 | U11: 108.1 | V11: 107.4 | W11: 108 | Y11: NA | Z11: 106.5 | AB11: 106.1 | AD11: 105.1 | AF11: 104.4 | AH11: 104.5 | AJ11: 104.8 | AL11: 102.7 | AN11: 104.6 | AP11: 106.4
A12: Urban | B12: 2013 | C12: April | D12: =DATE(B12,MATCH(TRIM(C12),{"January","February","March","April","May","June","July","August","September","October","November","December"},0),1) -> 41365 | E12: 114.6 | F12: 113.4 | G12: 106 | H12: 104.7 | I12: 102.1 | J12: 109.5 | K12: 109.7 | L12: 104.6 | M12: 102 | N12: 103.5 | O12: 108.2 | P12: 110.6 | Q12: 108.8 | S12: 108.5 | U12: 107.9 | V12: 106.4 | W12: 107.7 | Y12: 100.5 | Z12: 106.4 | AB12: 106.5 | AD12: 105.7 | AF12: 105 | AH12: 104 | AJ12: 105.2 | AL12: 103.2 | AN12: 105.1 | AP12: 105.7
A13: Rural+Urban | B13: 2013 | C13: April | D13: =DATE(B13,MATCH(TRIM(C13),{"January","February","March","April","May","June","July","August","September","October","November","December"},0),1) -> 41365 | E13: 111.6 | F13: 110.9 | G13: 106.6 | H13: 105.7 | I13: 104.4 | J13: 108.9 | K13: 105.5 | L13: 105.3 | M13: 103.5 | N13: 103.3 | O13: 107.2 | P13: 109.6 | Q13: 107.7 | S13: 107.5 | U13: 108 | V13: 107 | W13: 107.9 | Y13: 100.5 | Z13: 106.5 | AB13: 106.3 | AD13: 105.3 | AF13: 104.7 | AH13: 104.2 | AJ13: 105 | AL13: 102.9 | AN13: 104.8 | AP13: 106.1
A14: Rural | B14: 2013 | C14: May | D14: =DATE(B14,MATCH(TRIM(C14),{"January","February","March","April","May","June","July","August","September","October","November","December"},0),1) -> 41395 | E14: 110.9 | F14: 109.8 | G14: 105.9 | H14: 107.5 | I14: 105.3 | J14: 108.1 | K14: 107.3 | L14: 106.1 | M14: 103.7 | N14: 104 | O14: 107.4 | P14: 109.9 | Q14: 108.1 | S14: 108.1 | U14: 108.8 | V14: 107.9 | W14: 108.6 | Y14: NA | Z14: 107.5 | AB14: 106.8 | AD14: 105.7 | AF14: 104.1 | AH14: 105 | AJ14: 105.5 | AL14: 102.1 | AN14: 104.8 | AP14: 107.2
A15: Urban | B15: 2013 | C15: May | D15: =DATE(B15,MATCH(TRIM(C15),{"January","February","March","April","May","June","July","August","September","October","November","December"},0),1) -> 41395 | E15: 115.4 | F15: 114.2 | G15: 102.7 | H15: 105.5 | I15: 101.5 | J15: 110.6 | K15: 123.7 | L15: 105.2 | M15: 101.9 | N15: 105 | O15: 109.1 | P15: 111.3 | Q15: 111.1 | S15: 109.8 | U15: 108.5 | V15: 106.7 | W15: 108.3 | Y15: 100.5 | Z15: 107.2 | AB15: 107.1 | AD15: 106.2 | AF15: 103.9 | AH15: 104.6 | AJ15: 105.7 | AL15: 102.6 | AN15: 104.9 | AP15: 106.6
A16: Rural+Urban | B16: 2013 | C16: May | D16: =DATE(B16,MATCH(TRIM(C16),{"January","February","March","April","May","June","July","August","September","October","November","December"},0),1) -> 41395 | E16: 112.3 | F16: 111.3 | G16: 104.7 | H16: 106.8 | I16: 103.9 | J16: 109.3 | K16: 112.9 | L16: 105.8 | M16: 103.1 | N16: 104.3 | O16: 108.1 | P16: 110.5 | Q16: 109.2 | S16: 108.6 | U16: 108.7 | V16: 107.4 | W16: 108.5 | Y16: 100.5 | Z16: 107.4 | AB16: 106.9 | AD16: 105.9 | AF16: 104 | AH16: 104.8 | AJ16: 105.6 | AL16: 102.3 | AN16: 104.8 | AP16: 106.9
A17: Rural | B17: 2013 | C17: June | D17: =DATE(B17,MATCH(TRIM(C17),{"January","February","March","April","May","June","July","August","September","October","November","December"},0),1) -> 41426 | E17: 112.3 | F17: 112.1 | G17: 108.1 | H17: 108.3 | I17: 105.9 | J17: 109.2 | K17: 118 | L17: 106.8 | M17: 104.1 | N17: 105.4 | O17: 108.2 | P17: 111 | Q17: 110.6 | S17: 109 | U17: 109.7 | V17: 108.8 | W17: 109.5 | Y17: NA | Z17: 108.5 | AB17: 107.5 | AD17: 106.3 | AF17: 105 | AH17: 105.6 | AJ17: 106.5 | AL17: 102.5 | AN17: 105.5 | AP17: 108.9
A18: Urban | B18: 2013 | C18: June | D18: =DATE(B18,MATCH(TRIM(C18),{"January","February","March","April","May","June","July","August","September","October","November","December"},0),1) -> 41426 | E18: 117 | F18: 120.1 | G18: 112.5 | H18: 107.3 | I18: 101.3 | J18: 112.4 | K18: 143.6 | L18: 105.4 | M18: 101.4 | N18: 106.4 | O18: 110 | P18: 112.2 | Q18: 115 | S18: 110.9 | U18: 109.2 | V18: 107.2 | W18: 108.9 | Y18: 106.6 | Z18: 108 | AB18: 107.7 | AD18: 106.5 | AF18: 105.2 | AH18: 105.2 | AJ18: 108.1 | AL18: 103.3 | AN18: 106.1 | AP18: 109.7
A19: Rural+Urban | B19: 2013 | C19: June | D19: =DATE(B19,MATCH(TRIM(C19),{"January","February","March","April","May","June","July","August","September","October","November","December"},0),1) -> 41426 | E19: 113.8 | F19: 114.9 | G19: 109.8 | H19: 107.9 | I19: 104.2 | J19: 110.7 | K19: 126.7 | L19: 106.3 | M19: 103.2 | N19: 105.7 | O19: 109 | P19: 111.6 | Q19: 112.2 | S19: 109.5 | U19: 109.5 | V19: 108.1 | W19: 109.3 | Y19: 106.6 | Z19: 108.3 | AB19: 107.6 | AD19: 106.4 | AF19: 105.1 | AH19: 105.4 | AJ19: 107.4 | AL19: 102.8 | AN19: 105.8 | AP19: 109.3
A20: Rural | B20: 2013 | C20: July | D20: =DATE(B20,MATCH(TRIM(C20),{"January","February","March","April","May","June","July","August","September","October","November","December"},0),1) -> 41456 | E20: 113.4 | F20: 114.9 | G20: 110.5 | H20: 109.3 | I20: 106.2 | J20: 110.3 | K20: 129.2 | L20: 107.1 | M20: 104.3 | N20: 106.4 | O20: 109.1 | P20: 112.1 | Q20: 113.1 | S20: 109.8 | U20: 110.5 | V20: 109.5 | W20: 110.3 | Y20: NA | Z20: 109.5 | AB20: 108.3 | AD20: 106.9 | AF20: 106.8 | AH20: 106.4 | AJ20: 107.8 | AL20: 102.5 | AN20: 106.5 | AP20: 110.7
A21: Urban | B21: 2013 | C21: July | D21: =DATE(B21,MATCH(TRIM(C21),{"January","February","March","April","May","June","July","August","September","October","November","December"},0),1) -> 41456 | E21: 117.8 | F21: 119.2 | G21: 114 | H21: 108.3 | I21: 101.1 | J21: 113.2 | K21: 160.9 | L21: 105.1 | M21: 101.3 | N21: 107.5 | O21: 110.4 | P21: 113.1 | Q21: 117.5 | S21: 111.7 | U21: 109.8 | V21: 107.8 | W21: 109.5 | Y21: 107.7 | Z21: 108.6 | AB21: 108.1 | AD21: 107.1 | AF21: 107.3 | AH21: 105.9 | AJ21: 110.1 | AL21: 103.2 | AN21: 107.3 | AP21: 111.4
A22: Rural+Urban | B22: 2013 | C22: July | D22: =DATE(B22,MATCH(TRIM(C22),{"January","February","March","April","May","June","July","August","September","October","November","December"},0),1) -> 41456 | E22: 114.8 | F22: 116.4 | G22: 111.9 | H22: 108.9 | I22: 104.3 | J22: 111.7 | K22: 140 | L22: 106.4 | M22: 103.3 | N22: 106.8 | O22: 109.6 | P22: 112.6 | Q22: 114.7 | S22: 110.3 | U22: 110.2 | V22: 108.8 | W22: 110 | Y22: 107.7 | Z22: 109.2 | AB22: 108.2 | AD22: 107 | AF22: 107.1 | AH22: 106.1 | AJ22: 109.1 | AL22: 102.8 | AN22: 106.9 | AP22: 111
A23: Rural | B23: 2013 | C23: August | D23: =DATE(B23,MATCH(TRIM(C23),{"January","February","March","April","May","June","July","August","September","October","November","December"},0),1) -> 41487 | E23: 114.3 | F23: 115.4 | G23: 111.1 | H23: 110 | I23: 106.4 | J23: 110.8 | K23: 138.9 | L23: 107.4 | M23: 104.1 | N23: 106.9 | O23: 109.7 | P23: 112.6 | Q23: 114.9 | S23: 110.7 | U23: 111.3 | V23: 110.2 | W23: 111.1 | Y23: NA | Z23: 109.9 | AB23: 108.7 | AD23: 107.5 | AF23: 107.8 | AH23: 106.8 | AJ23: 108.7 | AL23: 105 | AN23: 107.5 | AP23: 112.1
A24: Urban | B24: 2013 | C24: August | D24: =DATE(B24,MATCH(TRIM(C24),{"January","February","March","April","May","June","July","August","September","October","November","December"},0),1) -> 41487 | E24: 118.3 | F24: 120.4 | G24: 112.7 | H24: 108.9 | I24: 101.1 | J24: 108.7 | K24: 177 | L24: 104.7 | M24: 101 | N24: 108.5 | O24: 110.9 | P24: 114.3 | Q24: 119.6 | S24: 112.4 | U24: 110.6 | V24: 108.3 | W24: 110.2 | Y24: 108.9 | Z24: 109.3 | AB24: 108.7 | AD24: 107.6 | AF24: 108.1 | AH24: 106.5 | AJ24: 110.8 | AL24: 106 | AN24: 108.3 | AP24: 112.7
A25: Rural+Urban | B25: 2013 | C25: August | D25: =DATE(B25,MATCH(TRIM(C25),{"January","February","March","April","May","June","July","August","September","October","November","December"},0),1) -> 41487 | E25: 115.6 | F25: 117.2 | G25: 111.7 | H25: 109.6 | I25: 104.5 | J25: 109.8 | K25: 151.8 | L25: 106.5 | M25: 103.1 | N25: 107.4 | O25: 110.2 | P25: 113.4 | Q25: 116.6 | S25: 111.2 | U25: 111 | V25: 109.4 | W25: 110.7 | Y25: 108.9 | Z25: 109.7 | AB25: 108.7 | AD25: 107.5 | AF25: 108 | AH25: 106.6 | AJ25: 109.9 | AL25: 105.4 | AN25: 107.9 | AP25: 112.4
A26: Rural | B26: 2013 | C26: September | D26: =DATE(B26,MATCH(TRIM(C26),{"January","February","March","April","May","June","July","August","September","October","November","December"},0),1) -> 41518 | E26: 115.4 | F26: 115.7 | G26: 111.7 | H26: 111 | I26: 107.4 | J26: 110.9 | K26: 154 | L26: 108.1 | M26: 104.2 | N26: 107.9 | O26: 110.4 | P26: 114 | Q26: 117.8 | S26: 111.7 | U26: 112.7 | V26: 111.4 | W26: 112.5 | Y26: NA | Z26: 111.1 | AB26: 109.6 | AD26: 108.3 | AF26: 109.3 | AH26: 107.7 | AJ26: 109.8 | AL26: 106.7 | AN26: 108.7 | AP26: 114.2
A27: Urban | B27: 2013 | C27: September | D27: =DATE(B27,MATCH(TRIM(C27),{"January","February","March","April","May","June","July","August","September","October","November","December"},0),1) -> 41518 | E27: 118.6 | F27: 119.1 | G27: 113.2 | H27: 109.6 | I27: 101.7 | J27: 103.2 | K27: 174.3 | L27: 105.1 | M27: 100.8 | N27: 109.1 | O27: 111.1 | P27: 115.4 | Q27: 119.2 | S27: 112.9 | U27: 111.4 | V27: 109 | W27: 111.1 | Y27: 109.7 | Z27: 109.5 | AB27: 109.6 | AD27: 107.9 | AF27: 110.4 | AH27: 107.4 | AJ27: 111.2 | AL27: 106.9 | AN27: 109.4 | AP27: 113.2
A28: Rural+Urban | B28: 2013 | C28: September | D28: =DATE(B28,MATCH(TRIM(C28),{"January","February","March","April","May","June","July","August","September","October","November","December"},0),1) -> 41518 | E28: 116.4 | F28: 116.9 | G28: 112.3 | H28: 110.5 | I28: 105.3 | J28: 107.3 | K28: 160.9 | L28: 107.1 | M28: 103.1 | N28: 108.3 | O28: 110.7 | P28: 114.6 | Q28: 118.3 | S28: 112 | U28: 112.2 | V28: 110.4 | W28: 111.9 | Y28: 109.7 | Z28: 110.5 | AB28: 109.6 | AD28: 108.1 | AF28: 109.9 | AH28: 107.5 | AJ28: 110.6 | AL28: 106.8 | AN28: 109 | AP28: 113.7
A29: Rural | B29: 2013 | C29: October | D29: =DATE(B29,MATCH(TRIM(C29),{"January","February","March","April","May","June","July","August","September","October","November","December"},0),1) -> 41548 | E29: 116.3 | F29: 115.4 | G29: 112.6 | H29: 111.7 | I29: 107.7 | J29: 113.2 | K29: 164.9 | L29: 108.3 | M29: 103.9 | N29: 108.2 | O29: 111.1 | P29: 114.9 | Q29: 119.8 | S29: 112.2 | U29: 113.6 | V29: 112.3 | W29: 113.4 | Y29: NA | Z29: 111.6 | AB29: 110.4 | AD29: 108.9 | AF29: 109.3 | AH29: 108.3 | AJ29: 110.2 | AL29: 107.5 | AN29: 109.1 | AP29: 115.5
A30: Urban | B30: 2013 | C30: October | D30: =DATE(B30,MATCH(TRIM(C30),{"January","February","March","April","May","June","July","August","September","October","November","December"},0),1) -> 41548 | E30: 118.9 | F30: 118.1 | G30: 114.5 | H30: 110.4 | I30: 102.3 | J30: 106.2 | K30: 183.5 | L30: 105.3 | M30: 100.2 | N30: 109.6 | O30: 111.4 | P30: 116 | Q30: 120.8 | S30: 113.5 | U30: 112.5 | V30: 109.7 | W30: 112 | Y30: 110.5 | Z30: 109.7 | AB30: 110.2 | AD30: 108.2 | AF30: 109.7 | AH30: 108 | AJ30: 111.3 | AL30: 107.3 | AN30: 109.4 | AP30: 114
A31: Rural+Urban | B31: 2013 | C31: October | D31: =DATE(B31,MATCH(TRIM(C31),{"January","February","March","April","May","June","July","August","September","October","November","December"},0),1) -> 41548 | E31: 117.1 | F31: 116.3 | G31: 113.3 | H31: 111.2 | I31: 105.7 | J31: 109.9 | K31: 171.2 | L31: 107.3 | M31: 102.7 | N31: 108.7 | O31: 111.2 | P31: 115.4 | Q31: 120.2 | S31: 112.5 | U31: 113.2 | V31: 111.2 | W31: 112.8 | Y31: 110.5 | Z31: 110.9 | AB31: 110.3 | AD31: 108.6 | AF31: 109.5 | AH31: 108.1 | AJ31: 110.8 | AL31: 107.4 | AN31: 109.2 | AP31: 114.8
A32: Rural | B32: 2013 | C32: November | D32: =DATE(B32,MATCH(TRIM(C32),{"January","February","March","April","May","June","July","August","September","October","November","December"},0),1) -> 41579 | E32: 117.3 | F32: 114.9 | G32: 116.2 | H32: 112.8 | I32: 108.9 | J32: 116.6 | K32: 178.1 | L32: 109.1 | M32: 103.6 | N32: 109 | O32: 111.8 | P32: 116 | Q32: 122.5 | S32: 112.8 | U32: 114.6 | V32: 113.1 | W32: 114.4 | Y32: NA | Z32: 112.6 | AB32: 111.3 | AD32: 109.7 | AF32: 109.6 | AH32: 108.7 | AJ32: 111 | AL32: 108.2 | AN32: 109.8 | AP32: 117.4
A33: Urban | B33: 2013 | C33: November | D33: =DATE(B33,MATCH(TRIM(C33),{"January","February","March","April","May","June","July","August","September","October","November","December"},0),1) -> 41579 | E33: 119.8 | F33: 116.3 | G33: 122.6 | H33: 112 | I33: 103.2 | J33: 110 | K33: 192.8 | L33: 106.3 | M33: 99.5 | N33: 110.3 | O33: 111.8 | P33: 117.1 | Q33: 122.9 | S33: 114.1 | U33: 113.5 | V33: 110.3 | W33: 113 | Y33: 111.1 | Z33: 110 | AB33: 110.9 | AD33: 108.6 | AF33: 109.5 | AH33: 108.5 | AJ33: 111.3 | AL33: 107.9 | AN33: 109.6 | AP33: 115
A34: Rural+Urban | B34: 2013 | C34: November | D34: =DATE(B34,MATCH(TRIM(C34),{"January","February","March","April","May","June","July","August","September","October","November","December"},0),1) -> 41579 | E34: 118.1 | F34: 115.4 | G34: 118.7 | H34: 112.5 | I34: 106.8 | J34: 113.5 | K34: 183.1 | L34: 108.2 | M34: 102.2 | N34: 109.4 | O34: 111.8 | P34: 116.5 | Q34: 122.6 | S34: 113.1 | U34: 114.2 | V34: 111.9 | W34: 113.8 | Y34: 111.1 | Z34: 111.6 | AB34: 111.1 | AD34: 109.3 | AF34: 109.5 | AH34: 108.6 | AJ34: 111.2 | AL34: 108.1 | AN34: 109.7 | AP34: 116.3
A35: Rural | B35: 2013 | C35: December | D35: =DATE(B35,MATCH(TRIM(C35),{"January","February","March","April","May","June","July","August","September","October","November","December"},0),1) -> 41609 | E35: 118.4 | F35: 115.9 | G35: 120.4 | H35: 113.8 | I35: 109.5 | J35: 115.5 | K35: 145.7 | L35: 109.5 | M35: 102.9 | N35: 109.8 | O35: 112.1 | P35: 116.8 | Q35: 118.7 | S35: 113.6 | U35: 115.8 | V35: 114 | W35: 115.5 | Y35: NA | Z35: 112.8 | AB35: 112.1 | AD35: 110.1 | AF35: 109.9 | AH35: 109.2 | AJ35: 111.6 | AL35: 108.1 | AN35: 110.1 | AP35: 115.5
A36: Urban | B36: 2013 | C36: December | D36: =DATE(B36,MATCH(TRIM(C36),{"January","February","March","April","May","June","July","August","September","October","November","December"},0),1) -> 41609 | E36: 120.5 | F36: 118.1 | G36: 128.5 | H36: 112.8 | I36: 103.4 | J36: 110.7 | K36: 144.8 | L36: 107.1 | M36: 98.6 | N36: 111.9 | O36: 112.1 | P36: 118.1 | Q36: 117.8 | S36: 115 | U36: 114.2 | V36: 110.9 | W36: 113.7 | Y36: 110.7 | Z36: 110.4 | AB36: 111.3 | AD36: 109 | AF36: 109.7 | AH36: 108.9 | AJ36: 111.4 | AL36: 107.7 | AN36: 109.8 | AP36: 113.3
A37: Rural+Urban | B37: 2013 | C37: December | D37: =DATE(B37,MATCH(TRIM(C37),{"January","February","March","April","May","June","July","August","September","October","November","December"},0),1) -> 41609 | E37: 119.1 | F37: 116.7 | G37: 123.5 | H37: 113.4 | I37: 107.3 | J37: 113.3 | K37: 145.4 | L37: 108.7 | M37: 101.5 | N37: 110.5 | O37: 112.1 | P37: 117.4 | Q37: 118.4 | S37: 114 | U37: 115.2 | V37: 112.7 | W37: 114.8 | Y37: 110.7 | Z37: 111.9 | AB37: 111.7 | AD37: 109.7 | AF37: 109.8 | AH37: 109 | AJ37: 111.5 | AL37: 107.9 | AN37: 110 | AP37: 114.5
A38: Rural | B38: 2014 | C38: January | D38: =DATE(B38,MATCH(TRIM(C38),{"January","February","March","April","May","June","July","August","September","October","November","December"},0),1) -> 41640 | E38: 118.9 | F38: 117.1 | G38: 120.5 | H38: 114.4 | I38: 109 | J38: 115.5 | K38: 123.9 | L38: 109.6 | M38: 101.8 | N38: 110.2 | O38: 112.4 | P38: 117.3 | Q38: 116 | S38: 114 | U38: 116.5 | V38: 114.5 | W38: 116.2 | Y38: NA | Z38: 113 | AB38: 112.6 | AD38: 110.6 | AF38: 110.5 | AH38: 109.6 | AJ38: 111.8 | AL38: 108.3 | AN38: 110.6 | AP38: 114.2
A39: Urban | B39: 2014 | C39: January | D39: =DATE(B39,MATCH(TRIM(C39),{"January","February","March","April","May","June","July","August","September","October","November","December"},0),1) -> 41640 | E39: 121.2 | F39: 122 | G39: 129.9 | H39: 113.6 | I39: 102.9 | J39: 112.1 | K39: 118.9 | L39: 107.5 | M39: 96.9 | N39: 112.7 | O39: 112.1 | P39: 119 | Q39: 115.5 | S39: 115.7 | U39: 114.8 | V39: 111.3 | W39: 114.3 | Y39: 111.6 | Z39: 111 | AB39: 111.9 | AD39: 109.7 | AF39: 110.8 | AH39: 109.8 | AJ39: 111.5 | AL39: 108 | AN39: 110.5 | AP39: 112.9
A40: Rural+Urban | B40: 2014 | C40: January | D40: =DATE(B40,MATCH(TRIM(C40),{"January","February","March","April","May","June","July","August","September","October","November","December"},0),1) -> 41640 | E40: 119.6 | F40: 118.8 | G40: 124.1 | H40: 114.1 | I40: 106.8 | J40: 113.9 | K40: 122.2 | L40: 108.9 | M40: 100.2 | N40: 111 | O40: 112.3 | P40: 118.1 | Q40: 115.8 | S40: 114.5 | U40: 115.8 | V40: 113.2 | W40: 115.4 | Y40: 111.6 | Z40: 112.2 | AB40: 112.3 | AD40: 110.3 | AF40: 110.7 | AH40: 109.7 | AJ40: 111.6 | AL40: 108.2 | AN40: 110.6 | AP40: 113.6
A41: Rural | B41: 2014 | C41: February | D41: =DATE(B41,MATCH(TRIM(C41),{"January","February","March","April","May","June","July","August","September","October","November","December"},0),1) -> 41671 | E41: 119.4 | F41: 117.7 | G41: 121.2 | H41: 115 | I41: 109 | J41: 116.6 | K41: 116 | L41: 109.8 | M41: 101.1 | N41: 110.4 | O41: 112.9 | P41: 117.8 | Q41: 115.3 | S41: 114.2 | U41: 117.1 | V41: 114.5 | W41: 116.7 | Y41: NA | Z41: 113.2 | AB41: 112.9 | AD41: 110.9 | AF41: 110.8 | AH41: 109.9 | AJ41: 112 | AL41: 108.7 | AN41: 110.9 | AP41: 114
A42: Urban | B42: 2014 | C42: February | D42: =DATE(B42,MATCH(TRIM(C42),{"January","February","March","April","May","June","July","August","September","October","November","December"},0),1) -> 41671 | E42: 121.9 | F42: 122 | G42: 124.5 | H42: 115.2 | I42: 102.5 | J42: 114.1 | K42: 111.5 | L42: 108.2 | M42: 95.4 | N42: 113.5 | O42: 112.1 | P42: 119.9 | Q42: 115.2 | S42: 116.2 | U42: 115.3 | V42: 111.7 | W42: 114.7 | Y42: 112.5 | Z42: 111.1 | AB42: 112.6 | AD42: 110.4 | AF42: 111.3 | AH42: 110.3 | AJ42: 111.6 | AL42: 108.7 | AN42: 111 | AP42: 113.1
A43: Rural+Urban | B43: 2014 | C43: February | D43: =DATE(B43,MATCH(TRIM(C43),{"January","February","March","April","May","June","July","August","September","October","November","December"},0),1) -> 41671 | E43: 120.2 | F43: 119.2 | G43: 122.5 | H43: 115.1 | I43: 106.6 | J43: 115.4 | K43: 114.5 | L43: 109.3 | M43: 99.2 | N43: 111.4 | O43: 112.6 | P43: 118.8 | Q43: 115.3 | S43: 114.7 | U43: 116.4 | V43: 113.3 | W43: 115.9 | Y43: 112.5 | Z43: 112.4 | AB43: 112.8 | AD43: 110.7 | AF43: 111.1 | AH43: 110.1 | AJ43: 111.8 | AL43: 108.7 | AN43: 110.9 | AP43: 113.6
A44: Rural | B44: 2014 | C44: March | D44: =DATE(B44,MATCH(TRIM(C44),{"January","February","March","April","May","June","July","August","September","October","November","December"},0),1) -> 41699 | E44: 120.1 | F44: 118.1 | G44: 120.7 | H44: 116.1 | I44: 109.3 | J44: 119.6 | K44: 117.9 | L44: 110.2 | M44: 101.2 | N44: 110.7 | O44: 113 | P44: 118.3 | Q44: 116.2 | S44: 114.6 | U44: 117.5 | V44: 114.9 | W44: 117.2 | Y44: NA | Z44: 113.4 | AB44: 113.4 | AD44: 111.4 | AF44: 111.2 | AH44: 110.2 | AJ44: 112.4 | AL44: 108.9 | AN44: 111.3 | AP44: 114.6
A45: Urban | B45: 2014 | C45: March | D45: =DATE(B45,MATCH(TRIM(C45),{"January","February","March","April","May","June","July","August","September","October","November","December"},0),1) -> 41699 | E45: 122.1 | F45: 121.4 | G45: 121.5 | H45: 116.2 | I45: 102.8 | J45: 117.7 | K45: 113.3 | L45: 108.9 | M45: 96.3 | N45: 114.1 | O45: 112.2 | P45: 120.5 | Q45: 116 | S45: 116.7 | U45: 115.8 | V45: 112.1 | W45: 115.2 | Y45: 113.2 | Z45: 110.9 | AB45: 113 | AD45: 110.8 | AF45: 111.6 | AH45: 110.9 | AJ45: 111.8 | AL45: 109.2 | AN45: 111.4 | AP45: 113.7
A46: Rural+Urban | B46: 2014 | C46: March | D46: =DATE(B46,MATCH(TRIM(C46),{"January","February","March","April","May","June","July","August","September","October","November","December"},0),1) -> 41699 | E46: 120.7 | F46: 119.3 | G46: 121 | H46: 116.1 | I46: 106.9 | J46: 118.7 | K46: 116.3 | L46: 109.8 | M46: 99.6 | N46: 111.8 | O46: 112.7 | P46: 119.3 | Q46: 116.1 | S46: 115.2 | U46: 116.8 | V46: 113.7 | W46: 116.4 | Y46: 113.2 | Z46: 112.5 | AB46: 113.2 | AD46: 111.2 | AF46: 111.4 | AH46: 110.6 | AJ46: 112 | AL46: 109 | AN46: 111.3 | AP46: 114.2
A47: Rural | B47: 2014 | C47: April | D47: =DATE(B47,MATCH(TRIM(C47),{"January","February","March","April","May","June","July","August","September","October","November","December"},0),1) -> 41730 | E47: 120.2 | F47: 118.9 | G47: 118.1 | H47: 117 | I47: 109.7 | J47: 125.5 | K47: 120.5 | L47: 111 | M47: 102.6 | N47: 111.2 | O47: 113.5 | P47: 118.7 | Q47: 117.2 | S47: 115.4 | U47: 118.1 | V47: 116.1 | W47: 117.8 | Y47: NA | Z47: 113.4 | AB47: 113.7 | AD47: 111.8 | AF47: 111.2 | AH47: 110.5 | AJ47: 113 | AL47: 108.9 | AN47: 111.5 | AP47: 115.4
A48: Urban | B48: 2014 | C48: April | D48: =DATE(B48,MATCH(TRIM(C48),{"January","February","March","April","May","June","July","August","September","October","November","December"},0),1) -> 41730 | E48: 122.5 | F48: 121.7 | G48: 113.3 | H48: 117 | I48: 103.1 | J48: 126.7 | K48: 121.2 | L48: 111 | M48: 100.3 | N48: 115.3 | O48: 112.7 | P48: 121 | Q48: 118.2 | S48: 117.6 | U48: 116.3 | V48: 112.5 | W48: 115.7 | Y48: 113.9 | Z48: 110.9 | AB48: 113.4 | AD48: 111 | AF48: 111.2 | AH48: 111.2 | AJ48: 112.5 | AL48: 109.1 | AN48: 111.4 | AP48: 114.7
A49: Rural+Urban | B49: 2014 | C49: April | D49: =DATE(B49,MATCH(TRIM(C49),{"January","February","March","April","May","June","July","August","September","October","November","December"},0),1) -> 41730 | E49: 120.9 | F49: 119.9 | G49: 116.2 | H49: 117 | I49: 107.3 | J49: 126.1 | K49: 120.7 | L49: 111 | M49: 101.8 | N49: 112.6 | O49: 113.2 | P49: 119.8 | Q49: 117.6 | S49: 116 | U49: 117.4 | V49: 114.6 | W49: 117 | Y49: 113.9 | Z49: 112.5 | AB49: 113.6 | AD49: 111.5 | AF49: 111.2 | AH49: 110.9 | AJ49: 112.7 | AL49: 109 | AN49: 111.5 | AP49: 115.1
A50: Rural | B50: 2014 | C50: May | D50: =DATE(B50,MATCH(TRIM(C50),{"January","February","March","April","May","June","July","August","September","October","November","December"},0),1) -> 41760 | E50: 120.3 | F50: 120.2 | G50: 116.9 | H50: 118 | I50: 110.1 | J50: 126.3 | K50: 123.9 | L50: 111.5 | M50: 103.5 | N50: 111.6 | O50: 114.2 | P50: 119.2 | Q50: 118.2 | S50: 116.3 | U50: 118.7 | V50: 116.8 | W50: 118.5 | Y50: NA | Z50: 113.4 | AB50: 114.1 | AD50: 112.1 | AF50: 111.4 | AH50: 110.9 | AJ50: 113.1 | AL50: 108.9 | AN50: 111.8 | AP50: 116
A51: Urban | B51: 2014 | C51: May | D51: =DATE(B51,MATCH(TRIM(C51),{"January","February","March","April","May","June","July","August","September","October","November","December"},0),1) -> 41760 | E51: 122.7 | F51: 124.1 | G51: 114.2 | H51: 119.1 | I51: 103.5 | J51: 129.2 | K51: 127 | L51: 112.6 | M51: 101.3 | N51: 117 | O51: 112.9 | P51: 121.7 | Q51: 120 | S51: 118.3 | U51: 116.8 | V51: 112.9 | W51: 116.2 | Y51: 114.3 | Z51: 111.1 | AB51: 114.1 | AD51: 111.2 | AF51: 111.3 | AH51: 111.5 | AJ51: 112.9 | AL51: 109.3 | AN51: 111.7 | AP51: 115.6
A52: Rural+Urban | B52: 2014 | C52: May | D52: =DATE(B52,MATCH(TRIM(C52),{"January","February","March","April","May","June","July","August","September","October","November","December"},0),1) -> 41760 | E52: 121.1 | F52: 121.6 | G52: 115.9 | H52: 118.4 | I52: 107.7 | J52: 127.7 | K52: 125 | L52: 111.9 | M52: 102.8 | N52: 113.4 | O52: 113.7 | P52: 120.4 | Q52: 118.9 | S52: 116.8 | U52: 118 | V52: 115.2 | W52: 117.6 | Y52: 114.3 | Z52: 112.5 | AB52: 114.1 | AD52: 111.8 | AF52: 111.3 | AH52: 111.2 | AJ52: 113 | AL52: 109.1 | AN52: 111.8 | AP52: 115.8
A53: Rural | B53: 2014 | C53: June | D53: =DATE(B53,MATCH(TRIM(C53),{"January","February","March","April","May","June","July","August","September","October","November","December"},0),1) -> 41791 | E53: 120.7 | F53: 121.6 | G53: 116.1 | H53: 119.3 | I53: 110.3 | J53: 125.8 | K53: 129.3 | L53: 112.2 | M53: 103.6 | N53: 112.3 | O53: 114.9 | P53: 120.1 | Q53: 119.5 | S53: 117.3 | U53: 119.7 | V53: 117.3 | W53: 119.3 | Y53: NA | Z53: 114.4 | AB53: 114.9 | AD53: 112.8 | AF53: 112.2 | AH53: 111.4 | AJ53: 114.3 | AL53: 108 | AN53: 112.3 | AP53: 117
A54: Urban | B54: 2014 | C54: June | D54: =DATE(B54,MATCH(TRIM(C54),{"January","February","March","April","May","June","July","August","September","October","November","December"},0),1) -> 41791 | E54: 123.1 | F54: 125.9 | G54: 115.4 | H54: 120.4 | I54: 103.4 | J54: 131.2 | K54: 137.5 | L54: 112.8 | M54: 101.4 | N54: 118.3 | O54: 113.2 | P54: 122.4 | Q54: 122 | S54: 119 | U54: 117.4 | V54: 113.2 | W54: 116.7 | Y54: 113.9 | Z54: 111.2 | AB54: 114.3 | AD54: 111.4 | AF54: 111.5 | AH54: 111.8 | AJ54: 115.1 | AL54: 108.7 | AN54: 112.2 | AP54: 116.4
A55: Rural+Urban | B55: 2014 | C55: June | D55: =DATE(B55,MATCH(TRIM(C55),{"January","February","March","April","May","June","July","August","September","October","November","December"},0),1) -> 41791 | E55: 121.5 | F55: 123.1 | G55: 115.8 | H55: 119.7 | I55: 107.8 | J55: 128.3 | K55: 132.1 | L55: 112.4 | M55: 102.9 | N55: 114.3 | O55: 114.2 | P55: 121.2 | Q55: 120.4 | S55: 117.8 | U55: 118.8 | V55: 115.6 | W55: 118.3 | Y55: 113.9 | Z55: 113.2 | AB55: 114.6 | AD55: 112.3 | AF55: 111.8 | AH55: 111.6 | AJ55: 114.8 | AL55: 108.3 | AN55: 112.3 | AP55: 116.7
A56: Rural | B56: 2014 | C56: July | D56: =DATE(B56,MATCH(TRIM(C56),{"January","February","March","April","May","June","July","August","September","October","November","December"},0),1) -> 41821 | E56: 121.7 | F56: 122.5 | G56: 117.7 | H56: 120.6 | I56: 110.4 | J56: 129.1 | K56: 150.1 | L56: 113.2 | M56: 104.8 | N56: 113.3 | O56: 115.6 | P56: 120.9 | Q56: 123.3 | S56: 118 | U56: 120.7 | V56: 118.3 | W56: 120.3 | Y56: NA | Z56: 115.3 | AB56: 115.4 | AD56: 113.4 | AF56: 113.2 | AH56: 111.8 | AJ56: 115.5 | AL56: 108.8 | AN56: 113.1 | AP56: 119.5
A57: Urban | B57: 2014 | C57: July | D57: =DATE(B57,MATCH(TRIM(C57),{"January","February","March","April","May","June","July","August","September","October","November","December"},0),1) -> 41821 | E57: 123.8 | F57: 126.4 | G57: 118 | H57: 121.6 | I57: 103.5 | J57: 133.7 | K57: 172.4 | L57: 113.1 | M57: 102.7 | N57: 120 | O57: 113.8 | P57: 123.4 | Q57: 127.1 | S57: 121 | U57: 118 | V57: 113.6 | W57: 117.4 | Y57: 114.8 | Z57: 111.6 | AB57: 114.9 | AD57: 111.5 | AF57: 113 | AH57: 112.4 | AJ57: 117.8 | AL57: 109.7 | AN57: 113.5 | AP57: 118.9
A58: Rural+Urban | B58: 2014 | C58: July | D58: =DATE(B58,MATCH(TRIM(C58),{"January","February","March","April","May","June","July","August","September","October","November","December"},0),1) -> 41821 | E58: 122.4 | F58: 123.9 | G58: 117.8 | H58: 121 | I58: 107.9 | J58: 131.2 | K58: 157.7 | L58: 113.2 | M58: 104.1 | N58: 115.5 | O58: 114.8 | P58: 122.1 | Q58: 124.7 | S58: 118.8 | U58: 119.6 | V58: 116.3 | W58: 119.1 | Y58: 114.8 | Z58: 113.9 | AB58: 115.2 | AD58: 112.7 | AF58: 113.1 | AH58: 112.1 | AJ58: 116.8 | AL58: 109.2 | AN58: 113.3 | AP58: 119.2
A59: Rural | B59: 2014 | C59: August | D59: =DATE(B59,MATCH(TRIM(C59),{"January","February","March","April","May","June","July","August","September","October","November","December"},0),1) -> 41852 | E59: 121.8 | F59: 122.8 | G59: 117.8 | H59: 121.9 | I59: 110.6 | J59: 129.7 | K59: 161.1 | L59: 114.1 | M59: 105.1 | N59: 114.6 | O59: 115.8 | P59: 121.7 | Q59: 125.3 | S59: 118.8 | U59: 120.9 | V59: 118.8 | W59: 120.7 | Y59: NA | Z59: 115.4 | AB59: 115.9 | AD59: 114 | AF59: 113.2 | AH59: 112.2 | AJ59: 116.2 | AL59: 109.4 | AN59: 113.5 | AP59: 120.7
A60: Urban | B60: 2014 | C60: August | D60: =DATE(B60,MATCH(TRIM(C60),{"January","February","March","April","May","June","July","August","September","October","November","December"},0),1) -> 41852 | E60: 124.8 | F60: 127.3 | G60: 116.5 | H60: 122.2 | I60: 103.6 | J60: 132.7 | K60: 181.9 | L60: 115.2 | M60: 102.7 | N60: 122.1 | O60: 114.4 | P60: 124.7 | Q60: 128.9 | S60: 123 | U60: 118.6 | V60: 114.1 | W60: 117.9 | Y60: 115.5 | Z60: 111.8 | AB60: 115.3 | AD60: 112.2 | AF60: 112.5 | AH60: 112.9 | AJ60: 119.2 | AL60: 110.5 | AN60: 113.9 | AP60: 119.9
A61: Rural+Urban | B61: 2014 | C61: August | D61: =DATE(B61,MATCH(TRIM(C61),{"January","February","March","April","May","June","July","August","September","October","November","December"},0),1) -> 41852 | E61: 122.7 | F61: 124.4 | G61: 117.3 | H61: 122 | I61: 108 | J61: 131.1 | K61: 168.2 | L61: 114.5 | M61: 104.3 | N61: 117.1 | O61: 115.2 | P61: 123.1 | Q61: 126.6 | S61: 119.9 | U61: 120 | V61: 116.8 | W61: 119.6 | Y61: 115.5 | Z61: 114 | AB61: 115.6 | AD61: 113.3 | AF61: 112.8 | AH61: 112.6 | AJ61: 118 | AL61: 109.9 | AN61: 113.7 | AP61: 120.3
A62: Rural | B62: 2014 | C62: September | D62: =DATE(B62,MATCH(TRIM(C62),{"January","February","March","April","May","June","July","August","September","October","November","December"},0),1) -> 41883 | E62: 122.3 | F62: 122.4 | G62: 117.8 | H62: 122.7 | I62: 110.4 | J62: 129.8 | K62: 158.8 | L62: 115 | M62: 104.7 | N62: 114.9 | O62: 116.5 | P62: 122.6 | Q62: 125.3 | S62: 119.5 | U62: 121.7 | V62: 119.2 | W62: 121.3 | Y62: NA | Z62: 115.8 | AB62: 116.7 | AD62: 114.5 | AF62: 112.8 | AH62: 112.6 | AJ62: 116.6 | AL62: 109.1 | AN62: 113.7 | AP62: 120.9
A63: Urban | B63: 2014 | C63: September | D63: =DATE(B63,MATCH(TRIM(C63),{"January","February","March","April","May","June","July","August","September","October","November","December"},0),1) -> 41883 | E63: 124.2 | F63: 125.4 | G63: 116.4 | H63: 122.7 | I63: 103.5 | J63: 124.5 | K63: 168.6 | L63: 116.9 | M63: 101.9 | N63: 122.9 | O63: 114.8 | P63: 125.2 | Q63: 126.7 | S63: 124.3 | U63: 119.2 | V63: 114.5 | W63: 118.4 | Y63: 116.1 | Z63: 111.8 | AB63: 115.5 | AD63: 112.3 | AF63: 111.2 | AH63: 113.4 | AJ63: 120 | AL63: 110 | AN63: 113.6 | AP63: 119.2
A64: Rural+Urban | B64: 2014 | C64: September | D64: =DATE(B64,MATCH(TRIM(C64),{"January","February","March","April","May","June","July","August","September","October","November","December"},0),1) -> 41883 | E64: 122.9 | F64: 123.5 | G64: 117.3 | H64: 122.7 | I64: 107.9 | J64: 127.3 | K64: 162.1 | L64: 115.6 | M64: 103.8 | N64: 117.6 | O64: 115.8 | P64: 123.8 | Q64: 125.8 | S64: 120.8 | U64: 120.7 | V64: 117.2 | W64: 120.1 | Y64: 116.1 | Z64: 114.3 | AB64: 116.1 | AD64: 113.7 | AF64: 112 | AH64: 113.1 | AJ64: 118.6 | AL64: 109.5 | AN64: 113.7 | AP64: 120.1
A65: Rural | B65: 2014 | C65: October | D65: =DATE(B65,MATCH(TRIM(C65),{"January","February","March","April","May","June","July","August","September","October","November","December"},0),1) -> 41913 | E65: 122.6 | F65: 122.5 | G65: 118.3 | H65: 123.2 | I65: 110.5 | J65: 128.9 | K65: 155.3 | L65: 115.5 | M65: 104 | N65: 115.3 | O65: 116.8 | P65: 123.2 | Q65: 125.1 | S65: 120 | U65: 122.7 | V65: 120.3 | W65: 122.3 | Y65: NA | Z65: 116.4 | AB65: 117.5 | AD65: 115.3 | AF65: 112.6 | AH65: 113 | AJ65: 116.9 | AL65: 109.3 | AN65: 114 | AP65: 121
A66: Urban | B66: 2014 | C66: October | D66: =DATE(B66,MATCH(TRIM(C66),{"January","February","March","April","May","June","July","August","September","October","November","December"},0),1) -> 41913 | E66: 124.6 | F66: 126.1 | G66: 117.8 | H66: 123.1 | I66: 103.5 | J66: 123.5 | K66: 159.6 | L66: 117.4 | M66: 101.2 | N66: 123.8 | O66: 115.2 | P66: 125.9 | Q66: 125.8 | S66: 124.3 | U66: 119.6 | V66: 114.9 | W66: 118.9 | Y66: 116.7 | Z66: 112 | AB66: 115.8 | AD66: 112.6 | AF66: 111 | AH66: 113.6 | AJ66: 120.2 | AL66: 110.1 | AN66: 113.7 | AP66: 119.1
A67: Rural+Urban | B67: 2014 | C67: October | D67: =DATE(B67,MATCH(TRIM(C67),{"January","February","March","April","May","June","July","August","September","October","November","December"},0),1) -> 41913 | E67: 123.2 | F67: 123.8 | G67: 118.1 | H67: 123.2 | I67: 107.9 | J67: 126.4 | K67: 156.8 | L67: 116.1 | M67: 103.1 | N67: 118.1 | O67: 116.1 | P67: 124.5 | Q67: 125.4 | S67: 121.1 | U67: 121.5 | V67: 118.1 | W67: 121 | Y67: 116.7 | Z67: 114.7 | AB67: 116.7 | AD67: 114.3 | AF67: 111.8 | AH67: 113.3 | AJ67: 118.8 | AL67: 109.6 | AN67: 113.9 | AP67: 120.1
A68: Rural | B68: 2014 | C68: November | D68: =DATE(B68,MATCH(TRIM(C68),{"January","February","March","April","May","June","July","August","September","October","November","December"},0),1) -> 41944 | E68: 122.7 | F68: 122.6 | G68: 119.9 | H68: 124 | I68: 110.5 | J68: 128.8 | K68: 152 | L68: 116.2 | M68: 103.3 | N68: 115.8 | O68: 116.8 | P68: 124.5 | Q68: 124.9 | S68: 120.8 | U68: 123.3 | V68: 120.5 | W68: 122.9 | Y68: NA | Z68: 117.3 | AB68: 118.1 | AD68: 115.9 | AF68: 112 | AH68: 113.3 | AJ68: 117.2 | AL68: 108.8 | AN68: 114.1 | AP68: 121.1
A69: Urban | B69: 2014 | C69: November | D69: =DATE(B69,MATCH(TRIM(C69),{"January","February","March","April","May","June","July","August","September","October","November","December"},0),1) -> 41944 | E69: 124.5 | F69: 125.6 | G69: 122.7 | H69: 124.6 | I69: 103.2 | J69: 122.2 | K69: 153.2 | L69: 119.3 | M69: 99.8 | N69: 124.6 | O69: 115.8 | P69: 126.9 | Q69: 125.4 | S69: 125.8 | U69: 120.3 | V69: 115.4 | W69: 119.5 | Y69: 117.1 | Z69: 112.6 | AB69: 116.4 | AD69: 113 | AF69: 109.7 | AH69: 114 | AJ69: 120.3 | AL69: 109.6 | AN69: 113.4 | AP69: 119
A70: Rural+Urban | B70: 2014 | C70: November | D70: =DATE(B70,MATCH(TRIM(C70),{"January","February","March","April","May","June","July","August","September","October","November","December"},0),1) -> 41944 | E70: 123.3 | F70: 123.7 | G70: 121 | H70: 124.2 | I70: 107.8 | J70: 125.7 | K70: 152.4 | L70: 117.2 | M70: 102.1 | N70: 118.7 | O70: 116.4 | P70: 125.6 | Q70: 125.1 | S70: 122.1 | U70: 122.1 | V70: 118.4 | W70: 121.6 | Y70: 117.1 | Z70: 115.5 | AB70: 117.3 | AD70: 114.8 | AF70: 110.8 | AH70: 113.7 | AJ70: 119 | AL70: 109.1 | AN70: 113.8 | AP70: 120.1
A71: Rural | B71: 2014 | C71: December | D71: =DATE(B71,MATCH(TRIM(C71),{"January","February","March","April","May","June","July","August","September","October","November","December"},0),1) -> 41974 | E71: 122.4 | F71: 122.4 | G71: 121.8 | H71: 124.2 | I71: 110.2 | J71: 128.6 | K71: 140.3 | L71: 116.3 | M71: 102 | N71: 116 | O71: 117.3 | P71: 124.8 | Q71: 123.3 | S71: 121.7 | U71: 123.8 | V71: 120.6 | W71: 123.3 | Y71: NA | Z71: 117.4 | AB71: 118.2 | AD71: 116.2 | AF71: 111.5 | AH71: 113.3 | AJ71: 117.7 | AL71: 109.4 | AN71: 114.2 | AP71: 120.3
A72: Urban | B72: 2014 | C72: December | D72: =DATE(B72,MATCH(TRIM(C72),{"January","February","March","April","May","June","July","August","September","October","November","December"},0),1) -> 41974 | E72: 124 | F72: 124.7 | G72: 126.3 | H72: 124.9 | I72: 103 | J72: 122.3 | K72: 141 | L72: 120.1 | M72: 97.8 | N72: 125.4 | O72: 116.1 | P72: 127.6 | Q72: 124 | S72: 126.4 | U72: 120.7 | V72: 115.8 | W72: 120 | Y72: 116.5 | Z72: 113 | AB72: 116.8 | AD72: 113.2 | AF72: 108.8 | AH72: 114.3 | AJ72: 120.7 | AL72: 110.4 | AN72: 113.4 | AP72: 118.4
A73: Rural+Urban | B73: 2014 | C73: December | D73: =DATE(B73,MATCH(TRIM(C73),{"January","February","March","April","May","June","July","August","September","October","November","December"},0),1) -> 41974 | E73: 122.9 | F73: 123.2 | G73: 123.5 | H73: 124.5 | I73: 107.6 | J73: 125.7 | K73: 140.5 | L73: 117.6 | M73: 100.6 | N73: 119.1 | O73: 116.8 | P73: 126.1 | Q73: 123.6 | S73: 123 | U73: 122.6 | V73: 118.6 | W73: 122 | Y73: 116.5 | Z73: 115.7 | AB73: 117.5 | AD73: 115.1 | AF73: 110.1 | AH73: 113.9 | AJ73: 119.5 | AL73: 109.8 | AN73: 113.8 | AP73: 119.4
A74: Rural | B74: 2015 | C74: January | D74: =DATE(B74,MATCH(TRIM(C74),{"January","February","March","April","May","June","July","August","September","October","November","December"},0),1) -> 42005 | E74: 123.1 | F74: 123.1 | G74: 122.1 | H74: 124.9 | I74: 111 | J74: 130.4 | K74: 132.3 | L74: 117.2 | M74: 100.5 | N74: 117.2 | O74: 117.9 | P74: 125.6 | Q74: 122.8 | S74: 122.7 | U74: 124.4 | V74: 121.6 | W74: 124 | Y74: NA | Z74: 118.4 | AB74: 118.9 | AD74: 116.6 | AF74: 111 | AH74: 114 | AJ74: 118.2 | AL74: 110.2 | AN74: 114.5 | AP74: 120.3
A75: Urban | B75: 2015 | C75: January | D75: =DATE(B75,MATCH(TRIM(C75),{"January","February","March","April","May","June","July","August","September","October","November","December"},0),1) -> 42005 | E75: 124 | F75: 125.5 | G75: 126.6 | H75: 125.2 | I75: 104.3 | J75: 121.3 | K75: 134.4 | L75: 122.9 | M75: 96.1 | N75: 126.6 | O75: 116.5 | P75: 128 | Q75: 123.5 | S75: 127.4 | U75: 121 | V75: 116.1 | W75: 120.2 | Y75: 117.3 | Z75: 113.4 | AB75: 117.2 | AD75: 113.7 | AF75: 107.9 | AH75: 114.6 | AJ75: 120.8 | AL75: 111.4 | AN75: 113.4 | AP75: 118.5
A76: Rural+Urban | B76: 2015 | C76: January | D76: =DATE(B76,MATCH(TRIM(C76),{"January","February","March","April","May","June","July","August","September","October","November","December"},0),1) -> 42005 | E76: 123.4 | F76: 123.9 | G76: 123.8 | H76: 125 | I76: 108.5 | J76: 126.2 | K76: 133 | L76: 119.1 | M76: 99 | N76: 120.3 | O76: 117.3 | P76: 126.7 | Q76: 123.1 | S76: 124 | U76: 123.1 | V76: 119.3 | W76: 122.5 | Y76: 117.3 | Z76: 116.5 | AB76: 118.1 | AD76: 115.5 | AF76: 109.4 | AH76: 114.3 | AJ76: 119.7 | AL76: 110.7 | AN76: 114 | AP76: 119.5
A77: Rural | B77: 2015 | C77: February | D77: =DATE(B77,MATCH(TRIM(C77),{"January","February","March","April","May","June","July","August","September","October","November","December"},0),1) -> 42036 | E77: 123.4 | F77: 124.4 | G77: 122.1 | H77: 125.8 | I77: 111.5 | J77: 129.4 | K77: 128.2 | L77: 118.8 | M77: 100 | N77: 118.6 | O77: 118.8 | P77: 126.8 | Q77: 122.8 | S77: 124.2 | U77: 125.4 | V77: 122.7 | W77: 125 | Y77: NA | Z77: 120 | AB77: 119.6 | AD77: 117.7 | AF77: 110.9 | AH77: 114.8 | AJ77: 118.7 | AL77: 110.8 | AN77: 115 | AP77: 120.6
A78: Urban | B78: 2015 | C78: February | D78: =DATE(B78,MATCH(TRIM(C78),{"January","February","March","April","May","June","July","August","September","October","November","December"},0),1) -> 42036 | E78: 124.3 | F78: 126.5 | G78: 119.5 | H78: 125.6 | I78: 104.9 | J78: 121.6 | K78: 131.8 | L78: 125.1 | M78: 95 | N78: 127.7 | O78: 116.8 | P78: 128.6 | Q78: 123.7 | S78: 128.1 | U78: 121.3 | V78: 116.5 | W78: 120.6 | Y78: 118.1 | Z78: 114 | AB78: 117.7 | AD78: 114.1 | AF78: 106.8 | AH78: 114.9 | AJ78: 120.4 | AL78: 111.7 | AN78: 113.2 | AP78: 118.7
A79: Rural+Urban | B79: 2015 | C79: February | D79: =DATE(B79,MATCH(TRIM(C79),{"January","February","March","April","May","June","July","August","September","October","November","December"},0),1) -> 42036 | E79: 123.7 | F79: 125.1 | G79: 121.1 | H79: 125.7 | I79: 109.1 | J79: 125.8 | K79: 129.4 | L79: 120.9 | M79: 98.3 | N79: 121.6 | O79: 118 | P79: 127.6 | Q79: 123.1 | S79: 125.2 | U79: 123.8 | V79: 120.1 | W79: 123.3 | Y79: 118.1 | Z79: 117.7 | AB79: 118.7 | AD79: 116.3 | AF79: 108.7 | AH79: 114.9 | AJ79: 119.7 | AL79: 111.2 | AN79: 114.1 | AP79: 119.7
A80: Rural | B80: 2015 | C80: March | D80: =DATE(B80,MATCH(TRIM(C80),{"January","February","March","April","May","June","July","August","September","October","November","December"},0),1) -> 42064 | E80: 123.3 | F80: 124.7 | G80: 118.9 | H80: 126 | I80: 111.8 | J80: 130.9 | K80: 128 | L80: 119.9 | M80: 98.9 | N80: 119.4 | O80: 118.9 | P80: 127.7 | Q80: 123.1 | S80: 124.7 | U80: 126 | V80: 122.9 | W80: 125.5 | Y80: NA | Z80: 120.6 | AB80: 120.2 | AD80: 118.2 | AF80: 111.6 | AH80: 115.5 | AJ80: 119.4 | AL80: 110.8 | AN80: 115.5 | AP80: 121.1
A81: Urban | B81: 2015 | C81: March | D81: =DATE(B81,MATCH(TRIM(C81),{"January","February","March","April","May","June","July","August","September","October","November","December"},0),1) -> 42064 | E81: 124 | F81: 126.7 | G81: 113.5 | H81: 125.9 | I81: 104.8 | J81: 123.8 | K81: 131.4 | L81: 127.2 | M81: 93.2 | N81: 127.4 | O81: 117 | P81: 129.2 | Q81: 123.9 | S81: 128.8 | U81: 121.7 | V81: 116.9 | W81: 120.9 | Y81: 118.6 | Z81: 114.4 | AB81: 118 | AD81: 114.3 | AF81: 108.4 | AH81: 115.4 | AJ81: 120.6 | AL81: 111.3 | AN81: 113.8 | AP81: 119.1
A82: Rural+Urban | B82: 2015 | C82: March | D82: =DATE(B82,MATCH(TRIM(C82),{"January","February","March","April","May","June","July","August","September","October","November","December"},0),1) -> 42064 | E82: 123.5 | F82: 125.4 | G82: 116.8 | H82: 126 | I82: 109.2 | J82: 127.6 | K82: 129.2 | L82: 122.4 | M82: 97 | N82: 122.1 | O82: 118.1 | P82: 128.4 | Q82: 123.4 | S82: 125.8 | U82: 124.3 | V82: 120.4 | W82: 123.7 | Y82: 118.6 | Z82: 118.3 | AB82: 119.2 | AD82: 116.7 | AF82: 109.9 | AH82: 115.4 | AJ82: 120.1 | AL82: 111 | AN82: 114.7 | AP82: 120.2
A83: Rural | B83: 2015 | C83: April | D83: =DATE(B83,MATCH(TRIM(C83),{"January","February","March","April","May","June","July","August","September","October","November","December"},0),1) -> 42095 | E83: 123.3 | F83: 125.5 | G83: 117.2 | H83: 126.8 | I83: 111.9 | J83: 134.2 | K83: 127.5 | L83: 121.5 | M83: 97.8 | N83: 119.8 | O83: 119.4 | P83: 128.7 | Q83: 123.6 | S83: 125.7 | U83: 126.4 | V83: 123.3 | W83: 126 | Y83: NA | Z83: 121.2 | AB83: 120.9 | AD83: 118.6 | AF83: 111.9 | AH83: 116.2 | AJ83: 119.9 | AL83: 111.6 | AN83: 116 | AP83: 121.5
A84: Urban | B84: 2015 | C84: April | D84: =DATE(B84,MATCH(TRIM(C84),{"January","February","March","April","May","June","July","August","September","October","November","December"},0),1) -> 42095 | E84: 123.8 | F84: 128.2 | G84: 110 | H84: 126.3 | I84: 104.5 | J84: 130.6 | K84: 130.8 | L84: 131.3 | M84: 91.6 | N84: 127.7 | O84: 117.2 | P84: 129.5 | Q84: 124.6 | S84: 130.1 | U84: 122.1 | V84: 117.2 | W84: 121.3 | Y84: 119.2 | Z84: 114.7 | AB84: 118.4 | AD84: 114.6 | AF84: 108.4 | AH84: 115.6 | AJ84: 121.7 | AL84: 111.8 | AN84: 114.2 | AP84: 119.7
A85: Rural+Urban | B85: 2015 | C85: April | D85: =DATE(B85,MATCH(TRIM(C85),{"January","February","March","April","May","June","July","August","September","October","November","December"},0),1) -> 42095 | E85: 123.5 | F85: 126.4 | G85: 114.4 | H85: 126.6 | I85: 109.2 | J85: 132.5 | K85: 128.6 | L85: 124.8 | M85: 95.7 | N85: 122.4 | O85: 118.5 | P85: 129.1 | Q85: 124 | S85: 126.9 | U85: 124.7 | V85: 120.8 | W85: 124.1 | Y85: 119.2 | Z85: 118.7 | AB85: 119.7 | AD85: 117.1 | AF85: 110.1 | AH85: 115.9 | AJ85: 121 | AL85: 111.7 | AN85: 115.1 | AP85: 120.7
A86: Rural | B86: 2015 | C86: May | D86: =DATE(B86,MATCH(TRIM(C86),{"January","February","March","April","May","June","July","August","September","October","November","December"},0),1) -> 42125 | E86: 123.5 | F86: 127.1 | G86: 117.3 | H86: 127.7 | I86: 112.5 | J86: 134.1 | K86: 128.5 | L86: 124.3 | M86: 97.6 | N86: 120.7 | O86: 120.2 | P86: 129.8 | Q86: 124.4 | S86: 126.7 | U86: 127.3 | V86: 124.1 | W86: 126.8 | Y86: NA | Z86: 121.9 | AB86: 121.5 | AD86: 119.4 | AF86: 113.3 | AH86: 116.7 | AJ86: 120.5 | AL86: 112.3 | AN86: 116.9 | AP86: 122.4
A87: Urban | B87: 2015 | C87: May | D87: =DATE(B87,MATCH(TRIM(C87),{"January","February","March","April","May","June","July","August","September","October","November","December"},0),1) -> 42125 | E87: 123.8 | F87: 129.7 | G87: 111.3 | H87: 126.6 | I87: 105.2 | J87: 130.8 | K87: 135.6 | L87: 142.6 | M87: 90.8 | N87: 128.8 | O87: 117.7 | P87: 129.9 | Q87: 126.1 | S87: 131.3 | U87: 122.4 | V87: 117.4 | W87: 121.6 | Y87: 119.6 | Z87: 114.9 | AB87: 118.7 | AD87: 114.9 | AF87: 110.8 | AH87: 116 | AJ87: 122 | AL87: 112.4 | AN87: 115.2 | AP87: 120.7
A88: Rural+Urban | B88: 2015 | C88: May | D88: =DATE(B88,MATCH(TRIM(C88),{"January","February","March","April","May","June","July","August","September","October","November","December"},0),1) -> 42125 | E88: 123.6 | F88: 128 | G88: 115 | H88: 127.3 | I88: 109.8 | J88: 132.6 | K88: 130.9 | L88: 130.5 | M88: 95.3 | N88: 123.4 | O88: 119.2 | P88: 129.8 | Q88: 125 | S88: 127.9 | U88: 125.4 | V88: 121.3 | W88: 124.7 | Y88: 119.6 | Z88: 119.2 | AB88: 120.2 | AD88: 117.7 | AF88: 112 | AH88: 116.3 | AJ88: 121.4 | AL88: 112.3 | AN88: 116.1 | AP88: 121.6
A89: Rural | B89: 2015 | C89: June | D89: =DATE(B89,MATCH(TRIM(C89),{"January","February","March","April","May","June","July","August","September","October","November","December"},0),1) -> 42156 | E89: 124.1 | F89: 130.4 | G89: 122.1 | H89: 128.7 | I89: 114.1 | J89: 133.2 | K89: 135.2 | L89: 131.9 | M89: 96.3 | N89: 123 | O89: 121.1 | P89: 131.2 | Q89: 126.6 | S89: 128.2 | U89: 128.4 | V89: 125.1 | W89: 128 | Y89: NA | Z89: 122.6 | AB89: 122.8 | AD89: 120.4 | AF89: 114.2 | AH89: 117.9 | AJ89: 122 | AL89: 113 | AN89: 117.9 | AP89: 124.1
A90: Urban | B90: 2015 | C90: June | D90: =DATE(B90,MATCH(TRIM(C90),{"January","February","March","April","May","June","July","August","September","October","November","December"},0),1) -> 42156 | E90: 123.6 | F90: 134.4 | G90: 120.9 | H90: 127.3 | I90: 106 | J90: 132.3 | K90: 146.7 | L90: 148.1 | M90: 89.8 | N90: 130.5 | O90: 118 | P90: 130.5 | Q90: 128.5 | S90: 132.1 | U90: 123.2 | V90: 117.6 | W90: 122.3 | Y90: 119 | Z90: 115.1 | AB90: 119.2 | AD90: 115.4 | AF90: 111.7 | AH90: 116.2 | AJ90: 123.8 | AL90: 112.5 | AN90: 116 | AP90: 121.7
A91: Rural+Urban | B91: 2015 | C91: June | D91: =DATE(B91,MATCH(TRIM(C91),{"January","February","March","April","May","June","July","August","September","October","November","December"},0),1) -> 42156 | E91: 123.9 | F91: 131.8 | G91: 121.6 | H91: 128.2 | I91: 111.1 | J91: 132.8 | K91: 139.1 | L91: 137.4 | M91: 94.1 | N91: 125.5 | O91: 119.8 | P91: 130.9 | Q91: 127.3 | S91: 129.2 | U91: 126.4 | V91: 122 | W91: 125.7 | Y91: 119 | Z91: 119.8 | AB91: 121.1 | AD91: 118.5 | AF91: 112.9 | AH91: 116.9 | AJ91: 123.1 | AL91: 112.8 | AN91: 117 | AP91: 123
A92: Rural | B92: 2015 | C92: July | D92: =DATE(B92,MATCH(TRIM(C92),{"January","February","March","April","May","June","July","August","September","October","November","December"},0),1) -> 42186 | E92: 124 | F92: 131.5 | G92: 122 | H92: 128.7 | I92: 113.5 | J92: 133.3 | K92: 140.8 | L92: 133.8 | M92: 94.1 | N92: 123.4 | O92: 121 | P92: 131.7 | Q92: 127.5 | S92: 129.4 | U92: 128.8 | V92: 125.5 | W92: 128.3 | Y92: NA | Z92: 123 | AB92: 123 | AD92: 120.8 | AF92: 114.1 | AH92: 118 | AJ92: 122.9 | AL92: 112.7 | AN92: 118.1 | AP92: 124.7
A93: Urban | B93: 2015 | C93: July | D93: =DATE(B93,MATCH(TRIM(C93),{"January","February","March","April","May","June","July","August","September","October","November","December"},0),1) -> 42186 | E93: 123.2 | F93: 134.3 | G93: 119.5 | H93: 127.7 | I93: 106.3 | J93: 132.8 | K93: 153.5 | L93: 149.5 | M93: 85.7 | N93: 131.5 | O93: 118.3 | P93: 131.1 | Q93: 129.5 | S93: 133.1 | U93: 123.5 | V93: 117.9 | W93: 122.7 | Y93: 119.9 | Z93: 115.3 | AB93: 119.5 | AD93: 116 | AF93: 111.5 | AH93: 116.6 | AJ93: 125.4 | AL93: 111.7 | AN93: 116.3 | AP93: 122.4
A94: Rural+Urban | B94: 2015 | C94: July | D94: =DATE(B94,MATCH(TRIM(C94),{"January","February","March","April","May","June","July","August","September","October","November","December"},0),1) -> 42186 | E94: 123.7 | F94: 132.5 | G94: 121 | H94: 128.3 | I94: 110.9 | J94: 133.1 | K94: 145.1 | L94: 139.1 | M94: 91.3 | N94: 126.1 | O94: 119.9 | P94: 131.4 | Q94: 128.2 | S94: 130.4 | U94: 126.7 | V94: 122.3 | W94: 126.1 | Y94: 119.9 | Z94: 120.1 | AB94: 121.3 | AD94: 119 | AF94: 112.7 | AH94: 117.2 | AJ94: 124.4 | AL94: 112.3 | AN94: 117.2 | AP94: 123.6
A95: Rural | B95: 2015 | C95: August | D95: =DATE(B95,MATCH(TRIM(C95),{"January","February","March","April","May","June","July","August","September","October","November","December"},0),1) -> 42217 | E95: 124.7 | F95: 131.3 | G95: 121.3 | H95: 128.8 | I95: 114 | J95: 134.2 | K95: 153.6 | L95: 137.9 | M95: 93.1 | N95: 123.9 | O95: 121.5 | P95: 132.5 | Q95: 129.8 | S95: 130.1 | U95: 129.5 | V95: 126.3 | W95: 129 | Y95: NA | Z95: 123.8 | AB95: 123.7 | AD95: 121.1 | AF95: 113.6 | AH95: 118.5 | AJ95: 123.6 | AL95: 112.5 | AN95: 118.2 | AP95: 126.1
A96: Urban | B96: 2015 | C96: August | D96: =DATE(B96,MATCH(TRIM(C96),{"January","February","March","April","May","June","July","August","September","October","November","December"},0),1) -> 42217 | E96: 123.1 | F96: 131.7 | G96: 118.1 | H96: 128 | I96: 106.8 | J96: 130.1 | K96: 165.5 | L96: 156 | M96: 85.3 | N96: 132.7 | O96: 118.8 | P96: 131.7 | Q96: 131.1 | S96: 134.2 | U96: 123.7 | V96: 118.2 | W96: 122.9 | Y96: 120.9 | Z96: 115.3 | AB96: 120 | AD96: 116.6 | AF96: 109.9 | AH96: 117.2 | AJ96: 126.2 | AL96: 112 | AN96: 116.2 | AP96: 123.2
A97: Rural+Urban | B97: 2015 | C97: August | D97: =DATE(B97,MATCH(TRIM(C97),{"January","February","March","April","May","June","July","August","September","October","November","December"},0),1) -> 42217 | E97: 124.2 | F97: 131.4 | G97: 120.1 | H97: 128.5 | I97: 111.4 | J97: 132.3 | K97: 157.6 | L97: 144 | M97: 90.5 | N97: 126.8 | O97: 120.4 | P97: 132.1 | Q97: 130.3 | S97: 131.2 | U97: 127.2 | V97: 122.9 | W97: 126.6 | Y97: 120.9 | Z97: 120.6 | AB97: 122 | AD97: 119.4 | AF97: 111.7 | AH97: 117.8 | AJ97: 125.1 | AL97: 112.3 | AN97: 117.2 | AP97: 124.8
A98: Rural | B98: 2015 | C98: September | D98: =DATE(B98,MATCH(TRIM(C98),{"January","February","March","April","May","June","July","August","September","October","November","December"},0),1) -> 42248 | E98: 125.1 | F98: 131.1 | G98: 120.7 | H98: 129.2 | I98: 114.7 | J98: 132.3 | K98: 158.9 | L98: 142.1 | M98: 92.5 | N98: 125.4 | O98: 121.9 | P98: 132.7 | Q98: 131 | S98: 131 | U98: 130.4 | V98: 126.8 | W98: 129.9 | Y98: NA | Z98: 123.7 | AB98: 124.5 | AD98: 121.4 | AF98: 113.8 | AH98: 119.6 | AJ98: 124.5 | AL98: 113.7 | AN98: 118.8 | AP98: 127
A99: Urban | B99: 2015 | C99: September | D99: =DATE(B99,MATCH(TRIM(C99),{"January","February","March","April","May","June","July","August","September","October","November","December"},0),1) -> 42248 | E99: 123.4 | F99: 129 | G99: 115.6 | H99: 128.3 | I99: 107 | J99: 124 | K99: 168.5 | L99: 165.4 | M99: 86.3 | N99: 134.4 | O99: 119.1 | P99: 132.3 | Q99: 131.5 | S99: 134.7 | U99: 124 | V99: 118.6 | W99: 123.2 | Y99: 121.6 | Z99: 115.1 | AB99: 120.4 | AD99: 117.1 | AF99: 109.1 | AH99: 117.3 | AJ99: 126.5 | AL99: 112.9 | AN99: 116.2 | AP99: 123.5
A100: Rural+Urban | B100: 2015 | C100: September | D100: =DATE(B100,MATCH(TRIM(C100),{"January","February","March","April","May","June","July","August","September","October","November","December"},0),1) -> 42248 | E100: 124.6 | F100: 130.4 | G100: 118.7 | H100: 128.9 | I100: 111.9 | J100: 128.4 | K100: 162.2 | L100: 150 | M100: 90.4 | N100: 128.4 | O100: 120.7 | P100: 132.5 | Q100: 131.2 | S100: 132 | U100: 127.9 | V100: 123.4 | W100: 127.2 | Y100: 121.6 | Z100: 120.4 | AB100: 122.6 | AD100: 119.8 | AF100: 111.3 | AH100: 118.3 | AJ100: 125.7 | AL100: 113.4 | AN100: 117.5 | AP100: 125.4
...

Sheet Sheet5
A1: Sector | B1: Year | C1: Month | D1: Year-month | E1: Food and beverages | F1: MOM for Food nad beverages | G1: Pan, tobacco and intoxicants | H1: MOM for Pan,etc | I1: Clothing and footwear | J1: MOM for Clothing and Footwear | K1: Fuel and light | L1: MOM for Fuel and Light | M1: Household goods and services | N1: MOM for Household Goods and etc | O1: Health | P1: MOM for Health | Q1: Transport and communication | R1: MOM for Transport and etc | S1: Recreation and amusement | T1: MOM for recreation and amusement | U1: Education | V1: MOM for eduction | W1: Personal care and effects | X1: MOM for Personal care and effect | Y1: Miscellaneous | Z1: MOM for Miscellinous | AA1: General index | AB1: MOM for Genral index | AC1: Crude Oil | AD1: MOM of crude oil | AG1: broader categories | AH1: correltion
A2: Rural+Urban | B2: 2021 | C2: January | D2: 44197 | E2: 161 | G2: 186.5 | I2: 154.2 | K2: 147.9 | M2: 150 | O2: 159.3 | Q2: 141.9 | S2: 149.6 | U2: 159.2 | W2: 156.8 | Y2: 151.9 | AA2: 157.3 | AC2: =VLOOKUP(D2,'crude oil'!A1:E28,4,0) -> 54.79
A3: Rural+Urban | B3: 2021 | C3: February | D3: 44228 | E3: 156.9 | F3: =(E3-E2)/E2 -> -0.025465839 | G3: 188.3 | H3: =(G3-G2)/G2 -> 0.0096514745 | I3: 155.8 | J3: =(I3-I2)/I2 -> 0.010376135 | K3: 152.4 | L3: =(K3-K2)/K2 -> 0.030425963 | M3: 150.9 | N3: =(M3-M2)/M2 -> 0.006 | O3: 161.3 | P3: =(O3-O2)/O2 -> 0.012554928 | Q3: 145.1 | R3: =(Q3-Q2)/Q2 -> 0.022551092 | S3: 151.5 | T3: =(S3-S2)/S2 -> 0.012700535 | U3: 159.5 | V3: =(U3-U2)/U2 -> 0.0018844221 | W3: 155.8 | X3: =(W3-W2)/W2 -> -0.006377551 | Y3: 153.4 | Z3: =(Y3-Y2)/Y2 -> 0.0098749177 | AA3: 156.6 | AB3: =(AA3-AA2)/AA2 -> -0.0044500954 | AC3: =VLOOKUP(D3,'crude oil'!A2:E29,4,0) -> 61.22 | AD3: =VLOOKUP(D3,'crude oil'!A2:E29,5,0) -> 0.11735718 | AG3: Food and Beverages | AH3: =CORREL(F:F,AD:AD) -> 0.10939845
A4: Rural+Urban | B4: 2021 | C4: March | D4: 44256 | E4: 156.7 | F4: =(E4-E3)/E3 -> -0.0012746973 | G4: 188.1 | H4: =(G4-G3)/G3 -> -0.0010621349 | I4: 156.4 | J4: =(I4-I3)/I3 -> 0.0038510911 | K4: 155.5 | L4: =(K4-K3)/K3 -> 0.020341207 | M4: 151.2 | N4: =(M4-M3)/M3 -> 0.0019880716 | O4: 161.7 | P4: =(O4-O3)/O3 -> 0.0024798512 | Q4: 146.2 | R4: =(Q4-Q3)/Q3 -> 0.0075809786 | S4: 152.6 | T4: =(S4-S3)/S3 -> 0.0072607261 | U4: 160.2 | V4: =(U4-U3)/U3 -> 0.0043887147 | W4: 153.8 | X4: =(W4-W3)/W3 -> -0.01283697 | Y4: 153.8 | Z4: =(Y4-Y3)/Y3 -> 0.0026075619 | AA4: 156.8 | AB4: =(AA4-AA3)/AA3 -> 0.0012771392 | AC4: =VLOOKUP(D4,'crude oil'!A3:E30,4,0) -> 64.73 | AD4: =VLOOKUP(D4,'crude oil'!A3:E30,5,0) -> 0.057334205 | AG4: Pan, Tobacco and Intoxicants | AH4: =CORREL(H:H,AD:AD) -> 0.13968414
A5: Rural+Urban | B5: 2021 | C5: April | D5: 44287 | E5: 158 | F5: =(E5-E4)/E4 -> 0.0082961072 | G5: 188.8 | H5: =(G5-G4)/G4 -> 0.0037214248 | I5: 157.3 | J5: =(I5-I4)/I4 -> 0.0057544757 | K5: 155.6 | L5: =(K5-K4)/K4 -> 0.00064308682 | M5: 151.8 | N5: =(M5-M4)/M4 -> 0.003968254 | O5: 162.3 | P5: =(O5-O4)/O4 -> 0.0037105751 | Q5: 146.6 | R5: =(Q5-Q4)/Q4 -> 0.0027359781 | S5: 153.2 | T5: =(S5-S4)/S4 -> 0.003931848 | U5: 160.3 | V5: =(U5-U4)/U4 -> 0.00062421973 | W5: 155.4 | X5: =(W5-W4)/W4 -> 0.010403121 | Y5: 154.4 | Z5: =(Y5-Y4)/Y4 -> 0.0039011704 | AA5: 157.8 | AB5: =(AA5-AA4)/AA4 -> 0.006377551 | AC5: =VLOOKUP(D5,'crude oil'!A4:E31,4,0) -> 63.4 | AD5: =VLOOKUP(D5,'crude oil'!A4:E31,5,0) -> -0.020546887 | AG5: Clothing and Footwear | AH5: =CORREL(J:J,AD:AD) -> 0.10496857
A6: Rural+Urban | B6: 2021 | C6: May | D6: 44317 | E6: 160.7 | F6: =(E6-E5)/E5 -> 0.017088608 | G6: 191.9 | H6: =(G6-G5)/G5 -> 0.016419492 | I6: 160.4 | J6: =(I6-I5)/I5 -> 0.019707565 | K6: 159.4 | L6: =(K6-K5)/K5 -> 0.024421594 | M6: 154.7 | N6: =(M6-M5)/M5 -> 0.019104084 | O6: 165.8 | P6: =(O6-O5)/O5 -> 0.021565003 | Q6: 148.9 | R6: =(Q6-Q5)/Q5 -> 0.01568895 | S6: 155.8 | T6: =(S6-S5)/S5 -> 0.016971279 | U6: 161.2 | V6: =(U6-U5)/U5 -> 0.0056144729 | W6: 158.6 | X6: =(W6-W5)/W5 -> 0.020592021 | Y6: 156.8 | Z6: =(Y6-Y5)/Y5 -> 0.015544041 | AA6: 160.4 | AB6: =(AA6-AA5)/AA5 -> 0.016476553 | AC6: =VLOOKUP(D6,'crude oil'!A5:E32,4,0) -> 66.95 | AD6: =VLOOKUP(D6,'crude oil'!A5:E32,5,0) -> 0.055993691 | AG6: Fuel and Light | AH6: =CORREL(L:L,AD:AD) -> 0.13261758
A7: Rural+Urban | B7: 2021 | C7: June | D7: 44348 | E7: 162.6 | F7: =(E7-E6)/E6 -> 0.011823273 | G7: 190.8 | H7: =(G7-G6)/G6 -> -0.0057321522 | I7: 160.7 | J7: =(I7-I6)/I6 -> 0.0018703242 | K7: 159.8 | L7: =(K7-K6)/K6 -> 0.0025094103 | M7: 154.8 | N7: =(M7-M6)/M6 -> 0.00064641241 | O7: 166.3 | P7: =(O7-O6)/O6 -> 0.0030156815 | Q7: 150.7 | R7: =(Q7-Q6)/Q6 -> 0.01208865 | S7: 154.9 | T7: =(S7-S6)/S6 -> -0.0057766367 | U7: 161.7 | V7: =(U7-U6)/U6 -> 0.003101737 | W7: 158.8 | X7: =(W7-W6)/W6 -> 0.001261034 | Y7: 157.6 | Z7: =(Y7-Y6)/Y6 -> 0.0051020408 | AA7: 161.3 | AB7: =(AA7-AA6)/AA6 -> 0.0056109726 | AC7: =VLOOKUP(D7,'crude oil'!A6:E33,4,0) -> 71.98 | AD7: =VLOOKUP(D7,'crude oil'!A6:E33,5,0) -> 0.075130695 | AG7: Household Goods and Services | AH7: =CORREL(N:N,AD:AD) -> -0.004421401
A8: Rural+Urban | B8: 2021 | C8: July | D8: 44378 | E8: 164 | F8: =(E8-E7)/E7 -> 0.0086100861 | G8: 191.2 | H8: =(G8-G7)/G7 -> 0.0020964361 | I8: 161.4 | J8: =(I8-I7)/I7 -> 0.0043559428 | K8: 160.7 | L8: =(K8-K7)/K7 -> 0.0056320401 | M8: 155.8 | N8: =(M8-M7)/M7 -> 0.0064599483 | O8: 167 | P8: =(O8-O7)/O7 -> 0.0042092604 | Q8: 153.1 | R8: =(Q8-Q7)/Q7 -> 0.01592568 | S8: 155.3 | T8: =(S8-S7)/S7 -> 0.0025823112 | U8: 163.2 | V8: =(U8-U7)/U7 -> 0.0092764378 | W8: 160.1 | X8: =(W8-W7)/W7 -> 0.008186398 | Y8: 159 | Z8: =(Y8-Y7)/Y7 -> 0.0088832487 | AA8: 162.5 | AB8: =(AA8-AA7)/AA7 -> 0.0074395536 | AC8: =VLOOKUP(D8,'crude oil'!A7:E34,4,0) -> 73.54 | AD8: =VLOOKUP(D8,'crude oil'!A7:E34,5,0) -> 0.021672687 | AG8: Health | AH8: =CORREL(P:P,AD:AD) -> 0.077797237
A9: Rural+Urban | B9: 2021 | C9: August | D9: 44409 | E9: 164 | F9: =(E9-E8)/E8 -> 0 | G9: 192.1 | H9: =(G9-G8)/G8 -> 0.004707113 | I9: 163.2 | J9: =(I9-I8)/I8 -> 0.011152416 | K9: 162.6 | L9: =(K9-K8)/K8 -> 0.011823273 | M9: 157.5 | N9: =(M9-M8)/M8 -> 0.010911425 | O9: 168.4 | P9: =(O9-O8)/O8 -> 0.0083832335 | Q9: 154 | R9: =(Q9-Q8)/Q8 -> 0.0058785108 | S9: 157.6 | T9: =(S9-S8)/S8 -> 0.014810045 | U9: 163.8 | V9: =(U9-U8)/U8 -> 0.0036764706 | W9: 160 | X9: =(W9-W8)/W8 -> -0.00062460962 | Y9: 160 | Z9: =(Y9-Y8)/Y8 -> 0.0062893082 | AA9: 163.2 | AB9: =(AA9-AA8)/AA8 -> 0.0043076923 | AC9: =VLOOKUP(D9,'crude oil'!A8:E35,4,0) -> 69.8 | AD9: =VLOOKUP(D9,'crude oil'!A8:E35,5,0) -> -0.050856677 | AG9: Transport and Communication | AH9: =CORREL(R:R,AD:AD) -> 0.097696081
A10: Rural+Urban | B10: 2021 | C10: September | D10: 44440 | E10: 164 | F10: =(E10-E9)/E9 -> 0 | G10: 192.1 | H10: =(G10-G9)/G9 -> 0 | I10: 163.3 | J10: =(I10-I9)/I9 -> 0.0006127451 | K10: 162.6 | L10: =(K10-K9)/K9 -> 0 | M10: 157.5 | N10: =(M10-M9)/M9 -> 0 | O10: 168.4 | P10: =(O10-O9)/O9 -> 0 | Q10: 154 | R10: =(Q10-Q9)/Q9 -> 0 | S10: 157.7 | T10: =(S10-S9)/S9 -> 0.00063451777 | U10: 163.7 | V10: =(U10-U9)/U9 -> -0.00061050061 | W10: 160 | X10: =(W10-W9)/W9 -> 0 | Y10: 160 | Z10: =(Y10-Y9)/Y9 -> 0 | AA10: 163.2 | AB10: =(AA10-AA9)/AA9 -> 0 | AC10: =VLOOKUP(D10,'crude oil'!A9:E36,4,0) -> 73.13 | AD10: =VLOOKUP(D10,'crude oil'!A9:E36,5,0) -> 0.047707736 | AG10: Recreation and Amusement | AH10: =CORREL(T:T,AD:AD) -> 0.12837906
A11: Rural+Urban | B11: 2021 | C11: October | D11: 44470 | E11: 167.7 | F11: =(E11-E10)/E10 -> 0.022560976 | G11: 192.7 | H11: =(G11-G10)/G10 -> 0.0031233732 | I11: 164.3 | J11: =(I11-I10)/I10 -> 0.0061236987 | K11: 164.2 | L11: =(K11-K10)/K10 -> 0.0098400984 | M11: 158.4 | N11: =(M11-M10)/M10 -> 0.0057142857 | O11: 169.1 | P11: =(O11-O10)/O10 -> 0.0041567696 | Q11: 155.7 | R11: =(Q11-Q10)/Q10 -> 0.011038961 | S11: 158.6 | T11: =(S11-S10)/S10 -> 0.0057070387 | U11: 163.9 | V11: =(U11-U10)/U10 -> 0.0012217471 | W11: 160.8 | X11: =(W11-W10)/W10 -> 0.005 | Y11: 161 | Z11: =(Y11-Y10)/Y10 -> 0.00625 | AA11: 165.5 | AB11: =(AA11-AA10)/AA10 -> 0.014093137 | AC11: =VLOOKUP(D11,'crude oil'!A10:E37,4,0) -> 82.11 | AD11: =VLOOKUP(D11,'crude oil'!A10:E37,5,0) -> 0.12279502 | AG11: Education | AH11: =CORREL(V:V,AD:AD) -> -0.15568221
A12: Rural+Urban | B12: 2021 | C12: November | D12: 44501 | E12: 169.7 | F12: =(E12-E11)/E11 -> 0.011926058 | G12: 192.9 | H12: =(G12-G11)/G11 -> 0.0010378827 | I12: 165.8 | J12: =(I12-I11)/I11 -> 0.0091296409 | K12: 163.9 | L12: =(K12-K11)/K11 -> -0.0018270402 | M12: 159.3 | N12: =(M12-M11)/M11 -> 0.0056818182 | O12: 169.9 | P12: =(O12-O11)/O11 -> 0.0047309284 | Q12: 154.8 | R12: =(Q12-Q11)/Q11 -> -0.0057803468 | S12: 159.8 | T12: =(S12-S11)/S11 -> 0.0075662043 | U12: 164.3 | V12: =(U12-U11)/U11 -> 0.0024405125 | W12: 162.2 | X12: =(W12-W11)/W11 -> 0.0087064677 | Y12: 161.4 | Z12: =(Y12-Y11)/Y11 -> 0.002484472 | AA12: 166.7 | AB12: =(AA12-AA11)/AA11 -> 0.0072507553 | AC12: =VLOOKUP(D12,'crude oil'!A11:E38,4,0) -> 80.64 | AD12: =VLOOKUP(D12,'crude oil'!A11:E38,5,0) -> -0.017902813 | AG12: Personal Care and Effects | AH12: =CORREL(X:X,AD:AD) -> -3.7153546e-05
A13: Rural+Urban | B13: 2021 | C13: December | D13: 44531 | E13: 168.2 | F13: =(E13-E12)/E12 -> -0.0088391279 | G13: 192.4 | H13: =(G13-G12)/G12 -> -0.0025920166 | I13: 167 | J13: =(I13-I12)/I12 -> 0.0072376357 | K13: 164.1 | L13: =(K13-K12)/K12 -> 0.0012202563 | M13: 160.2 | N13: =(M13-M12)/M12 -> 0.0056497175 | O13: 170.6 | P13: =(O13-O12)/O12 -> 0.0041200706 | Q13: 155.7 | R13: =(Q13-Q12)/Q12 -> 0.0058139535 | S13: 160.6 | T13: =(S13-S12)/S12 -> 0.0050062578 | U13: 164.4 | V13: =(U13-U12)/U12 -> 0.00060864273 | W13: 162.6 | X13: =(W13-W12)/W12 -> 0.0024660912 | Y13: 162 | Z13: =(Y13-Y12)/Y12 -> 0.0037174721 | AA13: 166.2 | AB13: =(AA13-AA12)/AA12 -> -0.0029994001 | AC13: =VLOOKUP(D13,'crude oil'!A12:E39,4,0) -> 73.3 | AD13: =VLOOKUP(D13,'crude oil'!A12:E39,5,0) -> -0.091021825 | AG13: Miscellaneous | AH13: =CORREL(Z:Z,AD:AD) -> 0.079750052
A14: Rural+Urban | B14: 2022 | C14: January | D14: 44562 | E14: 166.4 | F14: =(E14-E13)/E13 -> -0.010701546 | G14: 192.2 | H14: =(G14-G13)/G13 -> -0.001039501 | I14: 168.5 | J14: =(I14-I13)/I13 -> 0.0089820359 | K14: 164.2 | L14: =(K14-K13)/K13 -> 0.00060938452 | M14: 161.1 | N14: =(M14-M13)/M13 -> 0.0056179775 | O14: 171.4 | P14: =(O14-O13)/O13 -> 0.0046893318 | Q14: 156.5 | R14: =(Q14-Q13)/Q13 -> 0.0051380861 | S14: 161.2 | T14: =(S14-S13)/S13 -> 0.00373599 | U14: 164.7 | V14: =(U14-U13)/U13 -> 0.0018248175 | W14: 163 | X14: =(W14-W13)/W13 -> 0.0024600246 | Y14: 162.7 | Z14: =(Y14-Y13)/Y13 -> 0.0043209877 | AA14: 165.7 | AB14: =(AA14-AA13)/AA13 -> -0.0030084236 | AC14: =VLOOKUP(D14,'crude oil'!A13:E40,4,0) -> 84.67 | AD14: =VLOOKUP(D14,'crude oil'!A13:E40,5,0) -> 0.15511596 | AG14: General Index | AH14: =CORREL(AB:AB,AD:AD) -> 0.13192465
A15: Rural+Urban | B15: 2022 | C15: February | D15: 44593 | E15: 166.2 | F15: =(E15-E14)/E14 -> -0.0012019231 | G15: 192.8 | H15: =(G15-G14)/G14 -> 0.0031217482 | I15: 169.6 | J15: =(I15-I14)/I14 -> 0.0065281899 | K15: 165.7 | L15: =(K15-K14)/K14 -> 0.009135201 | M15: 161.8 | N15: =(M15-M14)/M14 -> 0.0043451273 | O15: 172.2 | P15: =(O15-O14)/O14 -> 0.0046674446 | Q15: 156.9 | R15: =(Q15-Q14)/Q14 -> 0.0025559105 | S15: 162.1 | T15: =(S15-S14)/S14 -> 0.0055831266 | U15: 165.4 | V15: =(U15-U14)/U14 -> 0.0042501518 | W15: 164.4 | X15: =(W15-W14)/W14 -> 0.0085889571 | Y15: 163.5 | Z15: =(Y15-Y14)/Y14 -> 0.0049170252 | AA15: 166.1 | AB15: =(AA15-AA14)/AA14 -> 0.0024140012 | AC15: =VLOOKUP(D15,'crude oil'!A14:E41,4,0) -> 94.07 | AD15: =VLOOKUP(D15,'crude oil'!A14:E41,5,0) -> 0.11101925
A16: Rural+Urban | B16: 2022 | C16: March | D16: 44621 | E16: 168.4 | F16: =(E16-E15)/E15 -> 0.013237064 | G16: 193.7 | H16: =(G16-G15)/G15 -> 0.0046680498 | I16: 171.1 | J16: =(I16-I15)/I15 -> 0.0088443396 | K16: 167.2 | L16: =(K16-K15)/K15 -> 0.0090525045 | M16: 162.8 | N16: =(M16-M15)/M15 -> 0.0061804697 | O16: 173 | P16: =(O16-O15)/O15 -> 0.0046457607 | Q16: 157.9 | R16: =(Q16-Q15)/Q15 -> 0.0063734863 | S16: 163.3 | T16: =(S16-S15)/S15 -> 0.0074028378 | U16: 166 | V16: =(U16-U15)/U15 -> 0.0036275695 | W16: 167.2 | X16: =(W16-W15)/W15 -> 0.01703163 | Y16: 164.6 | Z16: =(Y16-Y15)/Y15 -> 0.0067278287 | AA16: 167.7 | AB16: =(AA16-AA15)/AA15 -> 0.0096327514 | AC16: =VLOOKUP(D16,'crude oil'!A15:E42,4,0) -> 112.87 | AD16: =VLOOKUP(D16,'crude oil'!A15:E42,5,0) -> 0.19985117
A17: Rural+Urban | B17: 2022 | C17: April | D17: 44652 | E17: 170.8 | F17: =(E17-E16)/E16 -> 0.014251781 | G17: 193.9 | H17: =(G17-G16)/G16 -> 0.0010325245 | I17: 172.8 | J17: =(I17-I16)/I16 -> 0.0099357101 | K17: 172.2 | L17: =(K17-K16)/K16 -> 0.029904306 | M17: 164 | N17: =(M17-M16)/M16 -> 0.0073710074 | O17: 174 | P17: =(O17-O16)/O16 -> 0.0057803468 | Q17: 162.6 | R17: =(Q17-Q16)/Q16 -> 0.029765674 | S17: 164.4 | T17: =(S17-S16)/S16 -> 0.0067360686 | U17: 166.9 | V17: =(U17-U16)/U16 -> 0.0054216867 | W17: 168.8 | X17: =(W17-W16)/W16 -> 0.009569378 | Y17: 166.8 | Z17: =(Y17-Y16)/Y16 -> 0.013365735 | AA17: 170.1 | AB17: =(AA17-AA16)/AA16 -> 0.01431127 | AC17: =VLOOKUP(D17,'crude oil'!A16:E43,4,0) -> 102.97 | AD17: =VLOOKUP(D17,'crude oil'!A16:E43,5,0) -> -0.087711527
A18: Rural+Urban | B18: 2022 | C18: May | D18: 44682 | E18: 173.3 | F18: =(E18-E17)/E17 -> 0.014637002 | G18: 194.1 | H18: =(G18-G17)/G17 -> 0.0010314595 | I18: 174.6 | J18: =(I18-I17)/I17 -> 0.010416667 | K18: 174.6 | L18: =(K18-K17)/K17 -> 0.013937282 | M18: 165.2 | N18: =(M18-M17)/M17 -> 0.0073170732 | O18: 174.8 | P18: =(O18-O17)/O17 -> 0.0045977011 | Q18: 163 | R18: =(Q18-Q17)/Q17 -> 0.0024600246 | S18: 165.1 | T18: =(S18-S17)/S17 -> 0.0042579075 | U18: 167.9 | V18: =(U18-U17)/U17 -> 0.0059916117 | W18: 168.4 | X18: =(W18-W17)/W17 -> -0.0023696682 | Y18: 167.5 | Z18: =(Y18-Y17)/Y17 -> 0.0041966427 | AA18: 171.7 | AB18: =(AA18-AA17)/AA17 -> 0.0094062316 | AC18: =VLOOKUP(D18,'crude oil'!A17:E44,4,0) -> 109.51 | AD18: =VLOOKUP(D18,'crude oil'!A17:E44,5,0) -> 0.063513645
A19: Rural+Urban | B19: 2022 | C19: June | D19: 44713 | E19: 174.9 | F19: =(E19-E18)/E18 -> 0.0092325447 | G19: 194.3 | H19: =(G19-G18)/G18 -> 0.0010303967 | I19: 176 | J19: =(I19-I18)/I18 -> 0.0080183276 | K19: 176 | L19: =(K19-K18)/K18 -> 0.0080183276 | M19: 166.4 | N19: =(M19-M18)/M18 -> 0.0072639225 | O19: 175.4 | P19: =(O19-O18)/O18 -> 0.0034324943 | Q19: 161.1 | R19: =(Q19-Q18)/Q18 -> -0.011656442 | S19: 165.8 | T19: =(S19-S18)/S18 -> 0.0042398546 | U19: 169 | V19: =(U19-U18)/U18 -> 0.0065515188 | W19: 169.4 | X19: =(W19-W18)/W18 -> 0.0059382423 | Y19: 167.5 | Z19: =(Y19-Y18)/Y18 -> 0 | AA19: 172.6 | AB19: =(AA19-AA18)/AA18 -> 0.0052417006 | AC19: =VLOOKUP(D19,'crude oil'!A18:E45,4,0) -> 116.01 | AD19: =VLOOKUP(D19,'crude oil'!A18:E45,5,0) -> 0.05935531
A20: Rural+Urban | B20: 2022 | C20: July | D20: 44743 | E20: 175 | F20: =(E20-E19)/E19 -> 0.00057175529 | G20: 194.6 | H20: =(G20-G19)/G19 -> 0.0015440041 | I20: 177.3 | J20: =(I20-I19)/I19 -> 0.0073863636 | K20: 179.6 | L20: =(K20-K19)/K19 -> 0.020454545 | M20: 167.4 | N20: =(M20-M19)/M19 -> 0.0060096154 | O20: 176.1 | P20: =(O20-O19)/O19 -> 0.003990878 | Q20: 161.6 | R20: =(Q20-Q19)/Q19 -> 0.0031036623 | S20: 166.3 | T20: =(S20-S19)/S19 -> 0.0030156815 | U20: 171.4 | V20: =(U20-U19)/U19 -> 0.014201183 | W20: 169.7 | X20: =(W20-W19)/W19 -> 0.0017709563 | Y20: 168.4 | Z20: =(Y20-Y19)/Y19 -> 0.0053731343 | AA20: 173.4 | AB20: =(AA20-AA19)/AA19 -> 0.0046349942 | AC20: =VLOOKUP(D20,'crude oil'!A19:E46,4,0) -> 105.49 | AD20: =VLOOKUP(D20,'crude oil'!A19:E46,5,0) -> -0.090681838
A21: Rural+Urban | B21: 2022 | C21: August | D21: 44774 | E21: 176.3 | F21: =(E21-E20)/E20 -> 0.0074285714 | G21: 195 | H21: =(G21-G20)/G20 -> 0.0020554985 | I21: 178.5 | J21: =(I21-I20)/I20 -> 0.0067681895 | K21: 178.8 | L21: =(K21-K20)/K20 -> -0.004454343 | M21: 168.5 | N21: =(M21-M20)/M20 -> 0.0065710872 | O21: 176.8 | P21: =(O21-O20)/O20 -> 0.0039750142 | Q21: 161.9 | R21: =(Q21-Q20)/Q20 -> 0.0018564356 | S21: 166.9 | T21: =(S21-S20)/S20 -> 0.0036079375 | U21: 172.3 | V21: =(U21-U20)/U20 -> 0.0052508751 | W21: 171.2 | X21: =(W21-W20)/W20 -> 0.0088391279 | Y21: 169.1 | Z21: =(Y21-Y20)/Y20 -> 0.0041567696 | AA21: 174.3 | AB21: =(AA21-AA20)/AA20 -> 0.0051903114 | AC21: =VLOOKUP(D21,'crude oil'!A20:E47,4,0) -> 97.4 | AD21: =VLOOKUP(D21,'crude oil'!A20:E47,5,0) -> -0.076689734
A22: Rural+Urban | B22: 2022 | C22: September | D22: 44805 | E22: 177.8 | F22: =(E22-E21)/E21 -> 0.0085082246 | G22: 195.9 | H22: =(G22-G21)/G21 -> 0.0046153846 | I22: 179.9 | J22: =(I22-I21)/I21 -> 0.0078431373 | K22: 179.5 | L22: =(K22-K21)/K21 -> 0.0039149888 | M22: 169.5 | N22: =(M22-M21)/M21 -> 0.0059347181 | O22: 177.8 | P22: =(O22-O21)/O21 -> 0.0056561086 | Q22: 162.3 | R22: =(Q22-Q21)/Q21 -> 0.0024706609 | S22: 167.6 | T22: =(S22-S21)/S21 -> 0.0041941282 | U22: 173.1 | V22: =(U22-U21)/U21 -> 0.0046430644 | W22: 170.9 | X22: =(W22-W21)/W21 -> -0.0017523364 | Y22: 169.7 | Z22: =(Y22-Y21)/Y21 -> 0.0035481963 | AA22: 175.3 | AB22: =(AA22-AA21)/AA21 -> 0.0057372347 | AC22: =VLOOKUP(D22,'crude oil'!A21:E48,4,0) -> 90.71 | AD22: =VLOOKUP(D22,'crude oil'!A21:E48,5,0) -> -0.068685832
A23: Rural+Urban | B23: 2022 | C23: October | D23: 44835 | E23: 179.6 | F23: =(E23-E22)/E22 -> 0.010123735 | G23: 196.3 | H23: =(G23-G22)/G22 -> 0.0020418581 | I23: 181 | J23: =(I23-I22)/I22 -> 0.0061145081 | K23: 180.5 | L23: =(K23-K22)/K22 -> 0.0055710306 | M23: 170.4 | N23: =(M23-M22)/M22 -> 0.0053097345 | O23: 178.7 | P23: =(O23-O22)/O22 -> 0.0050618673 | Q23: 162.9 | R23: =(Q23-Q22)/Q22 -> 0.0036968577 | S23: 168.2 | T23: =(S23-S22)/S22 -> 0.0035799523 | U23: 173.4 | V23: =(U23-U22)/U22 -> 0.0017331023 | W23: 172.1 | X23: =(W23-W22)/W22 -> 0.0070216501 | Y23: 170.5 | Z23: =(Y23-Y22)/Y22 -> 0.0047142015 | AA23: 176.7 | AB23: =(AA23-AA22)/AA22 -> 0.0079863092 | AC23: =VLOOKUP(D23,'crude oil'!A22:E49,4,0) -> 91.7 | AD23: =VLOOKUP(D23,'crude oil'!A22:E49,5,0) -> 0.010913901
A24: Rural+Urban | B24: 2022 | C24: November | D24: 44866 | E24: 178.3 | F24: =(E24-E23)/E23 -> -0.0072383073 | G24: 196.9 | H24: =(G24-G23)/G23 -> 0.0030565461 | I24: 182.1 | J24: =(I24-I23)/I23 -> 0.0060773481 | K24: 181.3 | L24: =(K24-K23)/K23 -> 0.004432133 | M24: 171.4 | N24: =(M24-M23)/M23 -> 0.0058685446 | O24: 179.8 | P24: =(O24-O23)/O23 -> 0.006155568 | Q24: 163 | R24: =(Q24-Q23)/Q23 -> 0.00061387354 | S24: 168.5 | T24: =(S24-S23)/S23 -> 0.001783591 | U24: 173.7 | V24: =(U24-U23)/U23 -> 0.0017301038 | W24: 173.6 | X24: =(W24-W23)/W23 -> 0.0087158629 | Y24: 171.1 | Z24: =(Y24-Y23)/Y23 -> 0.0035190616 | AA24: 176.5 | AB24: =(AA24-AA23)/AA23 -> -0.0011318619 | AC24: =VLOOKUP(D24,'crude oil'!A23:E50,4,0) -> 87.55 | AD24: =VLOOKUP(D24,'crude oil'!A23:E50,5,0) -> -0.04525627
A25: Rural+Urban | B25: 2022 | C25: December | D25: 44896 | E25: 175.9 | F25: =(E25-E24)/E24 -> -0.01346046 | G25: 197.3 | H25: =(G25-G24)/G24 -> 0.0020314881 | I25: 183 | J25: =(I25-I24)/I24 -> 0.0049423394 | K25: 182 | L25: =(K25-K24)/K24 -> 0.0038610039 | M25: 172.1 | N25: =(M25-M24)/M24 -> 0.004084014 | O25: 181.1 | P25: =(O25-O24)/O24 -> 0.0072302558 | Q25: 163.4 | R25: =(Q25-Q24)/Q24 -> 0.0024539877 | S25: 168.9 | T25: =(S25-S24)/S24 -> 0.0023738872 | U25: 174.1 | V25: =(U25-U24)/U24 -> 0.002302821 | W25: 175.8 | X25: =(W25-W24)/W24 -> 0.012672811 | Y25: 172 | Z25: =(Y25-Y24)/Y24 -> 0.0052600818 | AA25: 175.7 | AB25: =(AA25-AA24)/AA24 -> -0.0045325779 | AC25: =VLOOKUP(D25,'crude oil'!A24:E51,4,0) -> 78.1 | AD25: =VLOOKUP(D25,'crude oil'!A24:E51,5,0) -> -0.10793832
A26: Rural+Urban | B26: 2023 | C26: January | D26: 44927 | E26: 176.7 | F26: =(E26-E25)/E25 -> 0.0045480387 | G26: 198.2 | H26: =(G26-G25)/G25 -> 0.0045615813 | I26: 183.8 | J26: =(I26-I25)/I25 -> 0.0043715847 | K26: 182 | L26: =(K26-K25)/K25 -> 0 | M26: 172.9 | N26: =(M26-M25)/M25 -> 0.0046484602 | O26: 182.3 | P26: =(O26-O25)/O25 -> 0.0066261734 | Q26: 163.6 | R26: =(Q26-Q25)/Q25 -> 0.0012239902 | S26: 169.5 | T26: =(S26-S25)/S25 -> 0.0035523979 | U26: 174.3 | V26: =(U26-U25)/U25 -> 0.0011487651 | W26: 178.6 | X26: =(W26-W25)/W25 -> 0.01592719 | Y26: 172.8 | Z26: =(Y26-Y25)/Y25 -> 0.0046511628 | AA26: 176.5 | AB26: =(AA26-AA25)/AA25 -> 0.0045532157 | AC26: =VLOOKUP(D26,'crude oil'!A25:E52,4,0) -> 80.92 | AD26: =VLOOKUP(D26,'crude oil'!A25:E52,5,0) -> 0.036107554
... A28: Rural+Urban | B28: 2023 | C28: March | D28: 44986 | E28: 177 | F28: =(E28-E27)/E27 -> 0 | G28: 199.5 | H28: =(G28-G27)/G27 -> 0 | I28: 185.1 | J28: =(I28-I27)/I27 -> 0 | K28: 181.9 | L28: =(K28-K27)/K27 -> -0.0010982976 | M28: 174.2 | N28: =(M28-M27)/M27 -> 0 | O28: 184.4 | P28: =(O28-O27)/O27 -> 0 | Q28: 164.2 | R28: =(Q28-Q27)/Q27 -> 0 | S28: 170.3 | T28: =(S28-S27)/S27 -> 0 | U28: 175 | V28: =(U28-U27)/U27 -> 0 | W28: 181 | X28: =(W28-W27)/W27 -> 0 | Y28: 174.1 | Z28: =(Y28-Y27)/Y27 -> 0 | AA28: 177.2 | AB28: =(AA28-AA27)/AA27 -> 0 | AC28: =VLOOKUP(D28,'crude oil'!A27:E54,4,0) -> 78.54 | AD28: =VLOOKUP(D28,'crude oil'!A27:E54,5,0) -> -0.045454545

Sheet crude oil
B1: Year | C1: month | D1: price | E1: MOM change
A2: =DATE(B2,MATCH(TRIM(C2),{"January","February","March","April","May","June","July","August","September","October","November","December"},0),1) -> 44197 | B2: 2021 | C2: January | D2: 54.79
A3: =DATE(B3,MATCH(TRIM(C3),{"January","February","March","April","May","June","July","August","September","October","November","December"},0),1) -> 44228 | B3: 2021 | C3: February | D3: 61.22 | E3: =(D3-D2)/D2 -> 0.11735718
A4: =DATE(B4,MATCH(TRIM(C4),{"January","February","March","April","May","June","July","August","September","October","November","December"},0),1) -> 44256 | B4: 2021 | C4: March | D4: 64.73 | E4: =(D4-D3)/D3 -> 0.057334205
A5: =DATE(B5,MATCH(TRIM(C5),{"January","February","March","April","May","June","July","August","September","October","November","December"},0),1) -> 44287 | B5: 2021 | C5: April | D5: 63.4 | E5: =(D5-D4)/D4 -> -0.020546887
A6: =DATE(B6,MATCH(TRIM(C6),{"January","February","March","April","May","June","July","August","September","October","November","December"},0),1) -> 44317 | B6: 2021 | C6: May | D6: 66.95 | E6: =(D6-D5)/D5 -> 0.055993691
A7: =DATE(B7,MATCH(TRIM(C7),{"January","February","March","April","May","June","July","August","September","October","November","December"},0),1) -> 44348 | B7: 2021 | C7: June | D7: 71.98 | E7: =(D7-D6)/D6 -> 0.075130695
A8: =DATE(B8,MATCH(TRIM(C8),{"January","February","March","April","May","June","July","August","September","October","November","December"},0),1) -> 44378 | B8: 2021 | C8: July | D8: 73.54 | E8: =(D8-D7)/D7 -> 0.021672687
A9: =DATE(B9,MATCH(TRIM(C9),{"January","February","March","April","May","June","July","August","September","October","November","December"},0),1) -> 44409 | B9: 2021 | C9: August | D9: 69.8 | E9: =(D9-D8)/D8 -> -0.050856677
A10: =DATE(B10,MATCH(TRIM(C10),{"January","February","March","April","May","June","July","August","September","October","November","December"},0),1) -> 44440 | B10: 2021 | C10: September | D10: 73.13 | E10: =(D10-D9)/D9 -> 0.047707736
A11: =DATE(B11,MATCH(TRIM(C11),{"January","February","March","April","May","June","July","August","September","October","November","December"},0),1) -> 44470 | B11: 2021 | C11: October | D11: 82.11 | E11: =(D11-D10)/D10 -> 0.12279502
A12: =DATE(B12,MATCH(TRIM(C12),{"January","February","March","April","May","June","July","August","September","October","November","December"},0),1) -> 44501 | B12: 2021 | C12: November | D12: 80.64 | E12: =(D12-D11)/D11 -> -0.017902813
A13: =DATE(B13,MATCH(TRIM(C13),{"January","February","March","April","May","June","July","August","September","October","November","December"},0),1) -> 44531 | B13: 2021 | C13: December | D13: 73.3 | E13: =(D13-D12)/D12 -> -0.091021825
A14: =DATE(B14,MATCH(TRIM(C14),{"January","February","March","April","May","June","July","August","September","October","November","December"},0),1) -> 44562 | B14: 2022 | C14: January | D14: 84.67 | E14: =(D14-D13)/D13 -> 0.15511596
... A28: =DATE(B28,MATCH(TRIM(C28),{"January","February","March","April","May","June","July","August","September","October","November","December"},0),1) -> 44986 | B28: 2023 | C28: March | D28: 78.54 | E28: =(D28-D27)/D27 -> -0.045454545

Sheet Data dictnory
A1: Column Name | B1: Column Definition
A2: Sector | B2: Represents the population sector or geographical category for which the CPI data is recorded, such as Rural, Urban, or Rural+Urban.
A3: Year | B3: The calendar year in which the CPI data was recorded.
A4: Month | B4: The month in which the CPI data was recorded.
A5: Cereals and products | B5: CPI index value representing changes in the prices of cereals and cereal-based products.
A6: Meat and fish | B6: CPI index value representing changes in the prices of meat and fish products.
A7: Egg | B7: CPI index value representing changes in the price of eggs.
A8: Milk and products | B8: CPI index value representing changes in the prices of milk and dairy products.
A9: Oils and fats | B9: CPI index value representing changes in the prices of edible oils and fats.
A10: Fruits | B10: CPI index value representing changes in the prices of fruits.
A11: Vegetables | B11: CPI index value representing changes in the prices of vegetables.
A12: Pulses and products | B12: CPI index value representing changes in the prices of pulses and pulse-based products.
... A31: General index | B31: Overall CPI index representing the combined price movement of the entire basket of goods and services.

Sheet Sheet1
A1: Q1 - Which broader category having higher contribution in CPI
M5: All years | AC5: Latest Month may 2023
X11: vs
M25: As we can see Pan,tabacco and intoxicants category having the higher contribution towards CPI 9.36% in yearly pattern and for latest month may 2023 it is 9.39%
A30: Q2 - Which Year having YOY growth more after 2017 also reasons
B34: Years | C34: Y-O-Y Growth | D34: Avg
B35: 2017 | D35: 133.38611
B36: 2018 | C36: =(D36-D35)/D35*100 -> 3.9609321 | D36: 138.66944
B37: 2019 | C37: =(D37-D36)/D36*100 -> 3.935855 | D37: 144.12727
B38: 2020 | C38: =(D38-D37)/D37*100 -> 6.3851394 | D38: 153.33
B39: 2021 | C39: =(D39-D38)/D38*100 -> 5.2740277 | D39: 161.41667
B40: 2022 | C40: =(D40-D39)/D39*100 -> 6.6029943 | D40: 172.075
B41: 2023 | C41: =(D41-D40)/D40*100 -> 3.1953121 | D41: 177.57333
I47: As we can see in year 2022 the yoy growth is 6.60% which is maximum among all other years
L49: possible reasons
L50: 1-Russia–Ukraine War
L51: 2-High Fuel Prices
L52: 3-Global Supply Chain Disruptions
L53: 4-Post-COVID Economic Recovery
A56: Q3
E81: Highest food inflation in month October 2022 and lowest is December 2022 | J81: October | K81: 0.97
J82: December | K82: -1.36
D87: B
G111: Food and beverages have 4.133 of absolute change while spices contribute most absolute change with 30.46
G120: Q4
I149: As per the change % Health and fuel and light is impact most due to covid 19 with 21.86% and 20.14%
A169: Q5
R176: broader categories | S176: correltion
R178: Food and Beverages | S178: =CORREL(Sheet5!F:F,Sheet5!AD:AD) -> 0.10939845
R179: Pan, Tobacco and Intoxicants | S179: =CORREL(Sheet5!H:H,Sheet5!AD:AD) -> 0.13968414
R180: Clothing and Footwear | S180: =CORREL(Sheet5!J:J,Sheet5!AD:AD) -> 0.10496857
R181: Fuel and Light | S181: =CORREL(Sheet5!L:L,Sheet5!AD:AD) -> 0.13261758
R182: Household Goods and Services | S182: =CORREL(Sheet5!N:N,Sheet5!AD:AD) -> -0.004421401
R183: Health | S183: =CORREL(Sheet5!P:P,Sheet5!AD:AD) -> 0.077797237
R184: Transport and Communication | S184: =CORREL(Sheet5!R:R,Sheet5!AD:AD) -> 0.097696081
R185: Recreation and Amusement | S185: =CORREL(Sheet5!T:T,Sheet5!AD:AD) -> 0.12837906
R186: Education | S186: =CORREL(Sheet5!V:V,Sheet5!AD:AD) -> -0.15568221
R187: Personal Care and Effects | S187: =CORREL(Sheet5!X:X,Sheet5!AD:AD) -> -3.7153546e-05
R188: Miscellaneous | S188: =CORREL(Sheet5!Z:Z,Sheet5!AD:AD) -> 0.079750052
R189: General Index | S189: =CORREL(Sheet5!AB:AB,Sheet5!AD:AD) -> 0.13192465
